[
 {
  "ID+後3碼": 498760125,
  "排名": 1,
  "ID": 498760,
  "姓名": "陳Ｏ樺",
  "經驗值": 22600,
  "獎項": "$8,000元",
  "冰粽": "已完成",
  "鹼粽": "已完成",
  "白粽": "已完成",
  "肉粽": "已完成",
  "嘉興粽": "已完成",
  "全粽達成1000經驗": 1000,
  "FUN粽任務經驗值(中)開啟狀態": "V",
  "FUN粽任務經驗值(中)達成率": "已完成",
  "FUN粽任務經驗值(易)開啟狀態": null,
  "FUN粽任務經驗值(易)達成率": 0
 },
 {
  "ID+後3碼": 899006068,
  "排名": 2,
  "ID": 899006,
  "姓名": "林Ｏ廷",
  "經驗值": 21700,
  "獎項": "$8,000元",
  "冰粽": "已完成",
  "鹼粽": "已完成",
  "白粽": "已完成",
  "肉粽": "已完成",
  "嘉興粽": "已完成",
  "全粽達成1000經驗": 1000,
  "FUN粽任務經驗值(中)開啟狀態": "V",
  "FUN粽任務經驗值(中)達成率": "已完成",
  "FUN粽任務經驗值(易)開啟狀態": null,
  "FUN粽任務經驗值(易)達成率": 0
 },
 {
  "ID+後3碼": 565836168,
  "排名": 3,
  "ID": 565836,
  "姓名": "賴Ｏ偉",
  "經驗值": 20990,
  "獎項": "$8,000元",
  "冰粽": "已完成",
  "鹼粽": "已完成",
  "白粽": "已完成",
  "肉粽": "已完成",
  "嘉興粽": "已完成",
  "全粽達成1000經驗": 1000,
  "FUN粽任務經驗值(中)開啟狀態": "V",
  "FUN粽任務經驗值(中)達成率": "已完成",
  "FUN粽任務經驗值(易)開啟狀態": null,
  "FUN粽任務經驗值(易)達成率": 0
 },
 {
  "ID+後3碼": 709680804,
  "排名": 4,
  "ID": 709680,
  "姓名": "黃Ｏ鈞",
  "經驗值": 20120,
  "獎項": "$5,000元",
  "冰粽": "已完成",
  "鹼粽": "已完成",
  "白粽": "已完成",
  "肉粽": "已完成",
  "嘉興粽": "已完成",
  "全粽達成1000經驗": 1000,
  "FUN粽任務經驗值(中)開啟狀態": "V",
  "FUN粽任務經驗值(中)達成率": "已完成",
  "FUN粽任務經驗值(易)開啟狀態": null,
  "FUN粽任務經驗值(易)達成率": 0
 },
 {
  "ID+後3碼": 948783764,
  "排名": 5,
  "ID": 948783,
  "姓名": "張Ｏ銘",
  "經驗值": 19830,
  "獎項": "$5,000元",
  "冰粽": "已完成",
  "鹼粽": "已完成",
  "白粽": "已完成",
  "肉粽": "已完成",
  "嘉興粽": "已完成",
  "全粽達成1000經驗": 1000,
  "FUN粽任務經驗值(中)開啟狀態": "V",
  "FUN粽任務經驗值(中)達成率": "已完成",
  "FUN粽任務經驗值(易)開啟狀態": null,
  "FUN粽任務經驗值(易)達成率": 0
 },
 {
  "ID+後3碼": 215154043,
  "排名": 6,
  "ID": 215154,
  "姓名": "蔡Ｏ賢",
  "經驗值": 19770,
  "獎項": "$5,000元",
  "冰粽": "已完成",
  "鹼粽": "已完成",
  "白粽": "已完成",
  "肉粽": "已完成",
  "嘉興粽": "已完成",
  "全粽達成1000經驗": 1000,
  "FUN粽任務經驗值(中)開啟狀態": "V",
  "FUN粽任務經驗值(中)達成率": "已完成",
  "FUN粽任務經驗值(易)開啟狀態": null,
  "FUN粽任務經驗值(易)達成率": 0
 },
 {
  "ID+後3碼": 846333798,
  "排名": 7,
  "ID": 846333,
  "姓名": "陳Ｏ涓",
  "經驗值": 19740,
  "獎項": "$5,000元",
  "冰粽": "已完成",
  "鹼粽": "已完成",
  "白粽": "已完成",
  "肉粽": "已完成",
  "嘉興粽": "已完成",
  "全粽達成1000經驗": 1000,
  "FUN粽任務經驗值(中)開啟狀態": "V",
  "FUN粽任務經驗值(中)達成率": "已完成",
  "FUN粽任務經驗值(易)開啟狀態": null,
  "FUN粽任務經驗值(易)達成率": 0
 },
 {
  "ID+後3碼": 1052390690,
  "排名": 8,
  "ID": 1052390,
  "姓名": "黃Ｏ儒",
  "經驗值": 19300,
  "獎項": "$5,000元",
  "冰粽": "已完成",
  "鹼粽": "已完成",
  "白粽": "已完成",
  "肉粽": "已完成",
  "嘉興粽": "已完成",
  "全粽達成1000經驗": 1000,
  "FUN粽任務經驗值(中)開啟狀態": "V",
  "FUN粽任務經驗值(中)達成率": "已完成",
  "FUN粽任務經驗值(易)開啟狀態": null,
  "FUN粽任務經驗值(易)達成率": 0
 },
 {
  "ID+後3碼": 171747416,
  "排名": 9,
  "ID": 171747,
  "姓名": "黃Ｏ義",
  "經驗值": 19170,
  "獎項": "$3,000元",
  "冰粽": "已完成",
  "鹼粽": "已完成",
  "白粽": 0,
  "肉粽": "已完成",
  "嘉興粽": "已完成",
  "全粽達成1000經驗": 0,
  "FUN粽任務經驗值(中)開啟狀態": "V",
  "FUN粽任務經驗值(中)達成率": "已完成",
  "FUN粽任務經驗值(易)開啟狀態": null,
  "FUN粽任務經驗值(易)達成率": 0
 },
 {
  "ID+後3碼": 707500426,
  "排名": 10,
  "ID": 707500,
  "姓名": "黃Ｏ良",
  "經驗值": 18860,
  "獎項": "$3,000元",
  "冰粽": "已完成",
  "鹼粽": "已完成",
  "白粽": "已完成",
  "肉粽": "已完成",
  "嘉興粽": "已完成",
  "全粽達成1000經驗": 1000,
  "FUN粽任務經驗值(中)開啟狀態": "V",
  "FUN粽任務經驗值(中)達成率": "已完成",
  "FUN粽任務經驗值(易)開啟狀態": null,
  "FUN粽任務經驗值(易)達成率": 0
 },
 {
  "ID+後3碼": 927510120,
  "排名": 11,
  "ID": 927510,
  "姓名": "李Ｏ偉",
  "經驗值": 18730,
  "獎項": "$3,000元",
  "冰粽": "已完成",
  "鹼粽": "已完成",
  "白粽": "已完成",
  "肉粽": "已完成",
  "嘉興粽": "已完成",
  "全粽達成1000經驗": 1000,
  "FUN粽任務經驗值(中)開啟狀態": "V",
  "FUN粽任務經驗值(中)達成率": "已完成",
  "FUN粽任務經驗值(易)開啟狀態": null,
  "FUN粽任務經驗值(易)達成率": 0
 },
 {
  "ID+後3碼": 844621086,
  "排名": 12,
  "ID": 844621,
  "姓名": "陳Ｏ合",
  "經驗值": 18470,
  "獎項": "$3,000元",
  "冰粽": "已完成",
  "鹼粽": "已完成",
  "白粽": "已完成",
  "肉粽": "已完成",
  "嘉興粽": "已完成",
  "全粽達成1000經驗": 1000,
  "FUN粽任務經驗值(中)開啟狀態": "V",
  "FUN粽任務經驗值(中)達成率": "已完成",
  "FUN粽任務經驗值(易)開啟狀態": null,
  "FUN粽任務經驗值(易)達成率": 0
 },
 {
  "ID+後3碼": 229265304,
  "排名": 13,
  "ID": 229265,
  "姓名": "方Ｏ博",
  "經驗值": 18330,
  "獎項": "$3,000元",
  "冰粽": "已完成",
  "鹼粽": "已完成",
  "白粽": "已完成",
  "肉粽": "已完成",
  "嘉興粽": "已完成",
  "全粽達成1000經驗": 1000,
  "FUN粽任務經驗值(中)開啟狀態": "V",
  "FUN粽任務經驗值(中)達成率": "已完成",
  "FUN粽任務經驗值(易)開啟狀態": null,
  "FUN粽任務經驗值(易)達成率": 0
 },
 {
  "ID+後3碼": 212141098,
  "排名": 14,
  "ID": 212141,
  "姓名": "吳Ｏ軒",
  "經驗值": 18090,
  "獎項": "家樂福Carrefour提貨券3000元",
  "冰粽": "已完成",
  "鹼粽": "已完成",
  "白粽": "已完成",
  "肉粽": "已完成",
  "嘉興粽": "已完成",
  "全粽達成1000經驗": 1000,
  "FUN粽任務經驗值(中)開啟狀態": "V",
  "FUN粽任務經驗值(中)達成率": "已完成",
  "FUN粽任務經驗值(易)開啟狀態": null,
  "FUN粽任務經驗值(易)達成率": 0
 },
 {
  "ID+後3碼": 842069664,
  "排名": 15,
  "ID": 842069,
  "姓名": "林Ｏ蓮",
  "經驗值": 18070,
  "獎項": "家樂福Carrefour提貨券3000元",
  "冰粽": "已完成",
  "鹼粽": "已完成",
  "白粽": "已完成",
  "肉粽": "已完成",
  "嘉興粽": "已完成",
  "全粽達成1000經驗": 1000,
  "FUN粽任務經驗值(中)開啟狀態": "V",
  "FUN粽任務經驗值(中)達成率": "已完成",
  "FUN粽任務經驗值(易)開啟狀態": null,
  "FUN粽任務經驗值(易)達成率": 0
 },
 {
  "ID+後3碼": 557587248,
  "排名": 16,
  "ID": 557587,
  "姓名": "鄭Ｏ昌",
  "經驗值": 18060,
  "獎項": "$1,000元",
  "冰粽": "已完成",
  "鹼粽": "已完成",
  "白粽": "已完成",
  "肉粽": "已完成",
  "嘉興粽": "已完成",
  "全粽達成1000經驗": 1000,
  "FUN粽任務經驗值(中)開啟狀態": "V",
  "FUN粽任務經驗值(中)達成率": "已完成",
  "FUN粽任務經驗值(易)開啟狀態": null,
  "FUN粽任務經驗值(易)達成率": 0
 },
 {
  "ID+後3碼": 859134919,
  "排名": 17,
  "ID": 859134,
  "姓名": "蕭Ｏ軒",
  "經驗值": 17960,
  "獎項": "$1,000元",
  "冰粽": "已完成",
  "鹼粽": "已完成",
  "白粽": "已完成",
  "肉粽": "已完成",
  "嘉興粽": "已完成",
  "全粽達成1000經驗": 1000,
  "FUN粽任務經驗值(中)開啟狀態": "V",
  "FUN粽任務經驗值(中)達成率": "已完成",
  "FUN粽任務經驗值(易)開啟狀態": null,
  "FUN粽任務經驗值(易)達成率": 0
 },
 {
  "ID+後3碼": 1113665238,
  "排名": 18,
  "ID": 1113665,
  "姓名": "陳Ｏ香",
  "經驗值": 17910,
  "獎項": "$1,000元",
  "冰粽": "已完成",
  "鹼粽": "已完成",
  "白粽": "已完成",
  "肉粽": "已完成",
  "嘉興粽": "已完成",
  "全粽達成1000經驗": 1000,
  "FUN粽任務經驗值(中)開啟狀態": "V",
  "FUN粽任務經驗值(中)達成率": "已完成",
  "FUN粽任務經驗值(易)開啟狀態": null,
  "FUN粽任務經驗值(易)達成率": 0
 },
 {
  "ID+後3碼": 121151788,
  "排名": 19,
  "ID": 121151,
  "姓名": "林Ｏ銘",
  "經驗值": 17870,
  "獎項": "$1,000元",
  "冰粽": "已完成",
  "鹼粽": "已完成",
  "白粽": "已完成",
  "肉粽": "已完成",
  "嘉興粽": "已完成",
  "全粽達成1000經驗": 1000,
  "FUN粽任務經驗值(中)開啟狀態": "V",
  "FUN粽任務經驗值(中)達成率": "已完成",
  "FUN粽任務經驗值(易)開啟狀態": null,
  "FUN粽任務經驗值(易)達成率": 0
 },
 {
  "ID+後3碼": 840561526,
  "排名": 20,
  "ID": 840561,
  "姓名": "蘇Ｏ欽",
  "經驗值": 17630,
  "獎項": "$1,000元",
  "冰粽": "已完成",
  "鹼粽": "已完成",
  "白粽": "已完成",
  "肉粽": "已完成",
  "嘉興粽": "已完成",
  "全粽達成1000經驗": 1000,
  "FUN粽任務經驗值(中)開啟狀態": "V",
  "FUN粽任務經驗值(中)達成率": "已完成",
  "FUN粽任務經驗值(易)開啟狀態": null,
  "FUN粽任務經驗值(易)達成率": 0
 },
 {
  "ID+後3碼": 186976075,
  "排名": 21,
  "ID": 186976,
  "姓名": "杜Ｏ平",
  "經驗值": 17570,
  "獎項": "$1,000元",
  "冰粽": "已完成",
  "鹼粽": "已完成",
  "白粽": "已完成",
  "肉粽": "已完成",
  "嘉興粽": "已完成",
  "全粽達成1000經驗": 1000,
  "FUN粽任務經驗值(中)開啟狀態": "V",
  "FUN粽任務經驗值(中)達成率": "已完成",
  "FUN粽任務經驗值(易)開啟狀態": null,
  "FUN粽任務經驗值(易)達成率": 0
 },
 {
  "ID+後3碼": 551977334,
  "排名": 22,
  "ID": 551977,
  "姓名": "黃Ｏ傑",
  "經驗值": 17430,
  "獎項": "$1,000元",
  "冰粽": "已完成",
  "鹼粽": "已完成",
  "白粽": "已完成",
  "肉粽": "已完成",
  "嘉興粽": "已完成",
  "全粽達成1000經驗": 1000,
  "FUN粽任務經驗值(中)開啟狀態": "V",
  "FUN粽任務經驗值(中)達成率": "已完成",
  "FUN粽任務經驗值(易)開啟狀態": null,
  "FUN粽任務經驗值(易)達成率": 0
 },
 {
  "ID+後3碼": 357048829,
  "排名": 23,
  "ID": 357048,
  "姓名": "陳Ｏ偉",
  "經驗值": 17250,
  "獎項": "$1,000元",
  "冰粽": "已完成",
  "鹼粽": "已完成",
  "白粽": "已完成",
  "肉粽": "已完成",
  "嘉興粽": "已完成",
  "全粽達成1000經驗": 1000,
  "FUN粽任務經驗值(中)開啟狀態": "V",
  "FUN粽任務經驗值(中)達成率": "已完成",
  "FUN粽任務經驗值(易)開啟狀態": null,
  "FUN粽任務經驗值(易)達成率": 0
 },
 {
  "ID+後3碼": 830020584,
  "排名": 24,
  "ID": 830020,
  "姓名": "葉Ｏ瑋",
  "經驗值": 17170,
  "獎項": "$1,000元",
  "冰粽": "已完成",
  "鹼粽": "已完成",
  "白粽": "已完成",
  "肉粽": "已完成",
  "嘉興粽": "已完成",
  "全粽達成1000經驗": 1000,
  "FUN粽任務經驗值(中)開啟狀態": "V",
  "FUN粽任務經驗值(中)達成率": "已完成",
  "FUN粽任務經驗值(易)開啟狀態": null,
  "FUN粽任務經驗值(易)達成率": 0
 },
 {
  "ID+後3碼": 919285293,
  "排名": 25,
  "ID": 919285,
  "姓名": "彭Ｏ筠",
  "經驗值": 17080,
  "獎項": "$1,000元",
  "冰粽": "已完成",
  "鹼粽": "已完成",
  "白粽": "已完成",
  "肉粽": "已完成",
  "嘉興粽": "已完成",
  "全粽達成1000經驗": 1000,
  "FUN粽任務經驗值(中)開啟狀態": "V",
  "FUN粽任務經驗值(中)達成率": "已完成",
  "FUN粽任務經驗值(易)開啟狀態": null,
  "FUN粽任務經驗值(易)達成率": 0
 },
 {
  "ID+後3碼": 690577282,
  "排名": 26,
  "ID": 690577,
  "姓名": "尹Ｏ詮",
  "經驗值": 17070,
  "獎項": "$888元",
  "冰粽": "已完成",
  "鹼粽": "已完成",
  "白粽": "已完成",
  "肉粽": "已完成",
  "嘉興粽": "已完成",
  "全粽達成1000經驗": 1000,
  "FUN粽任務經驗值(中)開啟狀態": "V",
  "FUN粽任務經驗值(中)達成率": "已完成",
  "FUN粽任務經驗值(易)開啟狀態": null,
  "FUN粽任務經驗值(易)達成率": 0
 },
 {
  "ID+後3碼": 165361267,
  "排名": 27,
  "ID": 165361,
  "姓名": "劉Ｏ文",
  "經驗值": 17020,
  "獎項": "$888元",
  "冰粽": "已完成",
  "鹼粽": "已完成",
  "白粽": "已完成",
  "肉粽": "已完成",
  "嘉興粽": "已完成",
  "全粽達成1000經驗": 1000,
  "FUN粽任務經驗值(中)開啟狀態": "V",
  "FUN粽任務經驗值(中)達成率": "已完成",
  "FUN粽任務經驗值(易)開啟狀態": null,
  "FUN粽任務經驗值(易)達成率": 0
 },
 {
  "ID+後3碼": 840252342,
  "排名": 28,
  "ID": 840252,
  "姓名": "楊Ｏ潔",
  "經驗值": 16960,
  "獎項": "$888元",
  "冰粽": "已完成",
  "鹼粽": "已完成",
  "白粽": "已完成",
  "肉粽": "已完成",
  "嘉興粽": "已完成",
  "全粽達成1000經驗": 1000,
  "FUN粽任務經驗值(中)開啟狀態": "V",
  "FUN粽任務經驗值(中)達成率": "已完成",
  "FUN粽任務經驗值(易)開啟狀態": null,
  "FUN粽任務經驗值(易)達成率": 0
 },
 {
  "ID+後3碼": 362994436,
  "排名": 29,
  "ID": 362994,
  "姓名": "廖Ｏ浤",
  "經驗值": 16810,
  "獎項": "$888元",
  "冰粽": "已完成",
  "鹼粽": "已完成",
  "白粽": "已完成",
  "肉粽": "已完成",
  "嘉興粽": "已完成",
  "全粽達成1000經驗": 1000,
  "FUN粽任務經驗值(中)開啟狀態": "V",
  "FUN粽任務經驗值(中)達成率": "已完成",
  "FUN粽任務經驗值(易)開啟狀態": null,
  "FUN粽任務經驗值(易)達成率": 0
 },
 {
  "ID+後3碼": 236897576,
  "排名": 30,
  "ID": 236897,
  "姓名": "葉ＯＯ翔",
  "經驗值": 16800,
  "獎項": "$888元",
  "冰粽": "已完成",
  "鹼粽": "已完成",
  "白粽": "已完成",
  "肉粽": "已完成",
  "嘉興粽": "已完成",
  "全粽達成1000經驗": 1000,
  "FUN粽任務經驗值(中)開啟狀態": "V",
  "FUN粽任務經驗值(中)達成率": "已完成",
  "FUN粽任務經驗值(易)開啟狀態": null,
  "FUN粽任務經驗值(易)達成率": 0
 },
 {
  "ID+後3碼": 331548141,
  "排名": 31,
  "ID": 331548,
  "姓名": "林Ｏ峰",
  "經驗值": 16790,
  "獎項": "$888元",
  "冰粽": "已完成",
  "鹼粽": "已完成",
  "白粽": "已完成",
  "肉粽": "已完成",
  "嘉興粽": "已完成",
  "全粽達成1000經驗": 1000,
  "FUN粽任務經驗值(中)開啟狀態": "V",
  "FUN粽任務經驗值(中)達成率": "已完成",
  "FUN粽任務經驗值(易)開啟狀態": null,
  "FUN粽任務經驗值(易)達成率": 0
 },
 {
  "ID+後3碼": 480461016,
  "排名": 32,
  "ID": 480461,
  "姓名": "陳Ｏ佐",
  "經驗值": 16780,
  "獎項": "$888元",
  "冰粽": "已完成",
  "鹼粽": "已完成",
  "白粽": "已完成",
  "肉粽": "已完成",
  "嘉興粽": "已完成",
  "全粽達成1000經驗": 1000,
  "FUN粽任務經驗值(中)開啟狀態": "V",
  "FUN粽任務經驗值(中)達成率": "已完成",
  "FUN粽任務經驗值(易)開啟狀態": null,
  "FUN粽任務經驗值(易)達成率": 0
 },
 {
  "ID+後3碼": 811016084,
  "排名": 33,
  "ID": 811016,
  "姓名": "許Ｏ昇",
  "經驗值": 16750,
  "獎項": "$888元",
  "冰粽": "已完成",
  "鹼粽": "已完成",
  "白粽": "已完成",
  "肉粽": "已完成",
  "嘉興粽": "已完成",
  "全粽達成1000經驗": 1000,
  "FUN粽任務經驗值(中)開啟狀態": "V",
  "FUN粽任務經驗值(中)達成率": "已完成",
  "FUN粽任務經驗值(易)開啟狀態": null,
  "FUN粽任務經驗值(易)達成率": 0
 },
 {
  "ID+後3碼": 1089279345,
  "排名": 34,
  "ID": 1089279,
  "姓名": "林Ｏ璋",
  "經驗值": 16730,
  "獎項": "$888元",
  "冰粽": "已完成",
  "鹼粽": "已完成",
  "白粽": "已完成",
  "肉粽": "已完成",
  "嘉興粽": "已完成",
  "全粽達成1000經驗": 1000,
  "FUN粽任務經驗值(中)開啟狀態": "V",
  "FUN粽任務經驗值(中)達成率": "已完成",
  "FUN粽任務經驗值(易)開啟狀態": null,
  "FUN粽任務經驗值(易)達成率": 0
 },
 {
  "ID+後3碼": 832018805,
  "排名": 35,
  "ID": 832018,
  "姓名": "黃Ｏ威",
  "經驗值": 16710,
  "獎項": "$888元",
  "冰粽": "已完成",
  "鹼粽": "已完成",
  "白粽": "已完成",
  "肉粽": "已完成",
  "嘉興粽": "已完成",
  "全粽達成1000經驗": 1000,
  "FUN粽任務經驗值(中)開啟狀態": "V",
  "FUN粽任務經驗值(中)達成率": "已完成",
  "FUN粽任務經驗值(易)開啟狀態": null,
  "FUN粽任務經驗值(易)達成率": 0
 },
 {
  "ID+後3碼": 891950698,
  "排名": 36,
  "ID": 891950,
  "姓名": "鄭Ｏ蓁",
  "經驗值": 16630,
  "獎項": "百變手持無線乾濕兩用車用吸塵器",
  "冰粽": "已完成",
  "鹼粽": "已完成",
  "白粽": "已完成",
  "肉粽": "已完成",
  "嘉興粽": "已完成",
  "全粽達成1000經驗": 1000,
  "FUN粽任務經驗值(中)開啟狀態": "V",
  "FUN粽任務經驗值(中)達成率": "已完成",
  "FUN粽任務經驗值(易)開啟狀態": null,
  "FUN粽任務經驗值(易)達成率": 0
 },
 {
  "ID+後3碼": 864807084,
  "排名": 37,
  "ID": 864807,
  "姓名": "黃Ｏ槐",
  "經驗值": 16470,
  "獎項": "百變手持無線乾濕兩用車用吸塵器",
  "冰粽": "已完成",
  "鹼粽": "已完成",
  "白粽": "已完成",
  "肉粽": "已完成",
  "嘉興粽": "已完成",
  "全粽達成1000經驗": 1000,
  "FUN粽任務經驗值(中)開啟狀態": "V",
  "FUN粽任務經驗值(中)達成率": "已完成",
  "FUN粽任務經驗值(易)開啟狀態": null,
  "FUN粽任務經驗值(易)達成率": 0
 },
 {
  "ID+後3碼": 209545658,
  "排名": 38,
  "ID": 209545,
  "姓名": "陳Ｏ怡",
  "經驗值": 16410,
  "獎項": "百變手持無線乾濕兩用車用吸塵器",
  "冰粽": "已完成",
  "鹼粽": "已完成",
  "白粽": "已完成",
  "肉粽": "已完成",
  "嘉興粽": "已完成",
  "全粽達成1000經驗": 1000,
  "FUN粽任務經驗值(中)開啟狀態": "V",
  "FUN粽任務經驗值(中)達成率": "已完成",
  "FUN粽任務經驗值(易)開啟狀態": null,
  "FUN粽任務經驗值(易)達成率": 0
 },
 {
  "ID+後3碼": 915674300,
  "排名": 39,
  "ID": 915674,
  "姓名": "林Ｏ煌",
  "經驗值": 16390,
  "獎項": "百變手持無線乾濕兩用車用吸塵器",
  "冰粽": "已完成",
  "鹼粽": "已完成",
  "白粽": "已完成",
  "肉粽": "已完成",
  "嘉興粽": "已完成",
  "全粽達成1000經驗": 1000,
  "FUN粽任務經驗值(中)開啟狀態": "V",
  "FUN粽任務經驗值(中)達成率": "已完成",
  "FUN粽任務經驗值(易)開啟狀態": null,
  "FUN粽任務經驗值(易)達成率": 0
 },
 {
  "ID+後3碼": 557648674,
  "排名": 40,
  "ID": 557648,
  "姓名": "童Ｏ瑋",
  "經驗值": 16330,
  "獎項": "統一超商100元虛擬商品卡",
  "冰粽": "已完成",
  "鹼粽": "已完成",
  "白粽": "已完成",
  "肉粽": "已完成",
  "嘉興粽": "已完成",
  "全粽達成1000經驗": 1000,
  "FUN粽任務經驗值(中)開啟狀態": "V",
  "FUN粽任務經驗值(中)達成率": "已完成",
  "FUN粽任務經驗值(易)開啟狀態": null,
  "FUN粽任務經驗值(易)達成率": 0
 },
 {
  "ID+後3碼": 177661320,
  "排名": 41,
  "ID": 177661,
  "姓名": "卓Ｏ傑",
  "經驗值": 16320,
  "獎項": "統一超商100元虛擬商品卡",
  "冰粽": "已完成",
  "鹼粽": "已完成",
  "白粽": "已完成",
  "肉粽": "已完成",
  "嘉興粽": "已完成",
  "全粽達成1000經驗": 1000,
  "FUN粽任務經驗值(中)開啟狀態": "V",
  "FUN粽任務經驗值(中)達成率": "已完成",
  "FUN粽任務經驗值(易)開啟狀態": null,
  "FUN粽任務經驗值(易)達成率": 0
 },
 {
  "ID+後3碼": 888906079,
  "排名": 42,
  "ID": 888906,
  "姓名": "李Ｏ翔",
  "經驗值": 16270,
  "獎項": "統一超商100元虛擬商品卡",
  "冰粽": "已完成",
  "鹼粽": "已完成",
  "白粽": "已完成",
  "肉粽": "已完成",
  "嘉興粽": "已完成",
  "全粽達成1000經驗": 1000,
  "FUN粽任務經驗值(中)開啟狀態": "V",
  "FUN粽任務經驗值(中)達成率": "已完成",
  "FUN粽任務經驗值(易)開啟狀態": null,
  "FUN粽任務經驗值(易)達成率": 0
 },
 {
  "ID+後3碼": 177839829,
  "排名": 43,
  "ID": 177839,
  "姓名": "羅Ｏ智",
  "經驗值": 16260,
  "獎項": "統一超商100元虛擬商品卡",
  "冰粽": "已完成",
  "鹼粽": "已完成",
  "白粽": "已完成",
  "肉粽": "已完成",
  "嘉興粽": "已完成",
  "全粽達成1000經驗": 1000,
  "FUN粽任務經驗值(中)開啟狀態": null,
  "FUN粽任務經驗值(中)達成率": 0,
  "FUN粽任務經驗值(易)開啟狀態": "V",
  "FUN粽任務經驗值(易)達成率": "已完成"
 },
 {
  "ID+後3碼": 886691564,
  "排名": 44,
  "ID": 886691,
  "姓名": "林Ｏ紅",
  "經驗值": 16240,
  "獎項": "統一超商100元虛擬商品卡",
  "冰粽": "已完成",
  "鹼粽": "已完成",
  "白粽": "已完成",
  "肉粽": "已完成",
  "嘉興粽": "已完成",
  "全粽達成1000經驗": 1000,
  "FUN粽任務經驗值(中)開啟狀態": "V",
  "FUN粽任務經驗值(中)達成率": "已完成",
  "FUN粽任務經驗值(易)開啟狀態": null,
  "FUN粽任務經驗值(易)達成率": 0
 },
 {
  "ID+後3碼": 593052101,
  "排名": 45,
  "ID": 593052,
  "姓名": "陳Ｏ豪",
  "經驗值": 16200,
  "獎項": "統一超商100元虛擬商品卡",
  "冰粽": "已完成",
  "鹼粽": "已完成",
  "白粽": "已完成",
  "肉粽": "已完成",
  "嘉興粽": "已完成",
  "全粽達成1000經驗": 1000,
  "FUN粽任務經驗值(中)開啟狀態": "V",
  "FUN粽任務經驗值(中)達成率": "已完成",
  "FUN粽任務經驗值(易)開啟狀態": null,
  "FUN粽任務經驗值(易)達成率": 0
 },
 {
  "ID+後3碼": 674193032,
  "排名": 46,
  "ID": 674193,
  "姓名": "林Ｏ信",
  "經驗值": 16190,
  "獎項": "統一超商100元虛擬商品卡",
  "冰粽": "已完成",
  "鹼粽": "已完成",
  "白粽": "已完成",
  "肉粽": "已完成",
  "嘉興粽": "已完成",
  "全粽達成1000經驗": 1000,
  "FUN粽任務經驗值(中)開啟狀態": "V",
  "FUN粽任務經驗值(中)達成率": "已完成",
  "FUN粽任務經驗值(易)開啟狀態": null,
  "FUN粽任務經驗值(易)達成率": 0
 },
 {
  "ID+後3碼": 1071177939,
  "排名": 47,
  "ID": 1071177,
  "姓名": "葉Ｏ嘉",
  "經驗值": 16070,
  "獎項": "統一超商100元虛擬商品卡",
  "冰粽": "已完成",
  "鹼粽": "已完成",
  "白粽": "已完成",
  "肉粽": "已完成",
  "嘉興粽": "已完成",
  "全粽達成1000經驗": 1000,
  "FUN粽任務經驗值(中)開啟狀態": "V",
  "FUN粽任務經驗值(中)達成率": "已完成",
  "FUN粽任務經驗值(易)開啟狀態": null,
  "FUN粽任務經驗值(易)達成率": 0
 },
 {
  "ID+後3碼": 994175965,
  "排名": 48,
  "ID": 994175,
  "姓名": "陳Ｏ雄",
  "經驗值": 16000,
  "獎項": "統一超商100元虛擬商品卡",
  "冰粽": "已完成",
  "鹼粽": "已完成",
  "白粽": "已完成",
  "肉粽": "已完成",
  "嘉興粽": "已完成",
  "全粽達成1000經驗": 1000,
  "FUN粽任務經驗值(中)開啟狀態": "V",
  "FUN粽任務經驗值(中)達成率": "已完成",
  "FUN粽任務經驗值(易)開啟狀態": null,
  "FUN粽任務經驗值(易)達成率": 0
 },
 {
  "ID+後3碼": 866448803,
  "排名": 49,
  "ID": 866448,
  "姓名": "柯Ｏ豪",
  "經驗值": 15970,
  "獎項": "統一超商100元虛擬商品卡",
  "冰粽": "已完成",
  "鹼粽": "已完成",
  "白粽": "已完成",
  "肉粽": "已完成",
  "嘉興粽": "已完成",
  "全粽達成1000經驗": 1000,
  "FUN粽任務經驗值(中)開啟狀態": "V",
  "FUN粽任務經驗值(中)達成率": "已完成",
  "FUN粽任務經驗值(易)開啟狀態": null,
  "FUN粽任務經驗值(易)達成率": 0
 },
 {
  "ID+後3碼": 500160288,
  "排名": 50,
  "ID": 500160,
  "姓名": "呂Ｏ維",
  "經驗值": 15970,
  "獎項": "統一超商100元虛擬商品卡",
  "冰粽": "已完成",
  "鹼粽": "已完成",
  "白粽": "已完成",
  "肉粽": "已完成",
  "嘉興粽": "已完成",
  "全粽達成1000經驗": 1000,
  "FUN粽任務經驗值(中)開啟狀態": "V",
  "FUN粽任務經驗值(中)達成率": "已完成",
  "FUN粽任務經驗值(易)開啟狀態": null,
  "FUN粽任務經驗值(易)達成率": 0
 },
 {
  "ID+後3碼": 840566538,
  "排名": 51,
  "ID": 840566,
  "姓名": "謝Ｏ澔",
  "經驗值": 15940,
  "獎項": "統一超商100元虛擬商品卡",
  "冰粽": "已完成",
  "鹼粽": "已完成",
  "白粽": "已完成",
  "肉粽": "已完成",
  "嘉興粽": "已完成",
  "全粽達成1000經驗": 1000,
  "FUN粽任務經驗值(中)開啟狀態": null,
  "FUN粽任務經驗值(中)達成率": 0,
  "FUN粽任務經驗值(易)開啟狀態": null,
  "FUN粽任務經驗值(易)達成率": 0
 },
 {
  "ID+後3碼": 790699377,
  "排名": 52,
  "ID": 790699,
  "姓名": "張Ｏ基",
  "經驗值": 15900,
  "獎項": "統一超商100元虛擬商品卡",
  "冰粽": "已完成",
  "鹼粽": "已完成",
  "白粽": "已完成",
  "肉粽": "已完成",
  "嘉興粽": "已完成",
  "全粽達成1000經驗": 1000,
  "FUN粽任務經驗值(中)開啟狀態": "V",
  "FUN粽任務經驗值(中)達成率": "已完成",
  "FUN粽任務經驗值(易)開啟狀態": null,
  "FUN粽任務經驗值(易)達成率": 0
 },
 {
  "ID+後3碼": 672525326,
  "排名": 53,
  "ID": 672525,
  "姓名": "陳Ｏ宗",
  "經驗值": 15880,
  "獎項": "統一超商100元虛擬商品卡",
  "冰粽": "已完成",
  "鹼粽": "已完成",
  "白粽": "已完成",
  "肉粽": "已完成",
  "嘉興粽": "已完成",
  "全粽達成1000經驗": 1000,
  "FUN粽任務經驗值(中)開啟狀態": "V",
  "FUN粽任務經驗值(中)達成率": "已完成",
  "FUN粽任務經驗值(易)開啟狀態": null,
  "FUN粽任務經驗值(易)達成率": 0
 },
 {
  "ID+後3碼": 1120044689,
  "排名": 54,
  "ID": 1120044,
  "姓名": "洪Ｏ翔",
  "經驗值": 15870,
  "獎項": "統一超商100元虛擬商品卡",
  "冰粽": "已完成",
  "鹼粽": "已完成",
  "白粽": "已完成",
  "肉粽": "已完成",
  "嘉興粽": "已完成",
  "全粽達成1000經驗": 1000,
  "FUN粽任務經驗值(中)開啟狀態": "V",
  "FUN粽任務經驗值(中)達成率": "已完成",
  "FUN粽任務經驗值(易)開啟狀態": null,
  "FUN粽任務經驗值(易)達成率": 0
 },
 {
  "ID+後3碼": 753796804,
  "排名": 55,
  "ID": 753796,
  "姓名": "邱Ｏ傑",
  "經驗值": 15830,
  "獎項": "統一超商100元虛擬商品卡",
  "冰粽": "已完成",
  "鹼粽": "已完成",
  "白粽": "已完成",
  "肉粽": "已完成",
  "嘉興粽": "已完成",
  "全粽達成1000經驗": 1000,
  "FUN粽任務經驗值(中)開啟狀態": "V",
  "FUN粽任務經驗值(中)達成率": "已完成",
  "FUN粽任務經驗值(易)開啟狀態": null,
  "FUN粽任務經驗值(易)達成率": 0
 },
 {
  "ID+後3碼": 979596820,
  "排名": 56,
  "ID": 979596,
  "姓名": "周Ｏ麟",
  "經驗值": 15730,
  "獎項": "統一超商100元虛擬商品卡",
  "冰粽": "已完成",
  "鹼粽": "已完成",
  "白粽": "已完成",
  "肉粽": "已完成",
  "嘉興粽": "已完成",
  "全粽達成1000經驗": 1000,
  "FUN粽任務經驗值(中)開啟狀態": null,
  "FUN粽任務經驗值(中)達成率": 0,
  "FUN粽任務經驗值(易)開啟狀態": "V",
  "FUN粽任務經驗值(易)達成率": "已完成"
 },
 {
  "ID+後3碼": 526705499,
  "排名": 57,
  "ID": 526705,
  "姓名": "鍾Ｏ毅",
  "經驗值": 15710,
  "獎項": "統一超商100元虛擬商品卡",
  "冰粽": 0.7,
  "鹼粽": "已完成",
  "白粽": "已完成",
  "肉粽": "已完成",
  "嘉興粽": "已完成",
  "全粽達成1000經驗": 0,
  "FUN粽任務經驗值(中)開啟狀態": "V",
  "FUN粽任務經驗值(中)達成率": "已完成",
  "FUN粽任務經驗值(易)開啟狀態": null,
  "FUN粽任務經驗值(易)達成率": 0
 },
 {
  "ID+後3碼": 1096903956,
  "排名": 58,
  "ID": 1096903,
  "姓名": "王Ｏ勳",
  "經驗值": 15710,
  "獎項": "統一超商100元虛擬商品卡",
  "冰粽": "已完成",
  "鹼粽": "已完成",
  "白粽": "已完成",
  "肉粽": "已完成",
  "嘉興粽": 0,
  "全粽達成1000經驗": 0,
  "FUN粽任務經驗值(中)開啟狀態": "V",
  "FUN粽任務經驗值(中)達成率": "已完成",
  "FUN粽任務經驗值(易)開啟狀態": null,
  "FUN粽任務經驗值(易)達成率": 0
 },
 {
  "ID+後3碼": 838594513,
  "排名": 59,
  "ID": 838594,
  "姓名": "黃Ｏ惠",
  "經驗值": 15710,
  "獎項": "統一超商100元虛擬商品卡",
  "冰粽": "已完成",
  "鹼粽": "已完成",
  "白粽": "已完成",
  "肉粽": "已完成",
  "嘉興粽": "已完成",
  "全粽達成1000經驗": 1000,
  "FUN粽任務經驗值(中)開啟狀態": "V",
  "FUN粽任務經驗值(中)達成率": "已完成",
  "FUN粽任務經驗值(易)開啟狀態": null,
  "FUN粽任務經驗值(易)達成率": 0
 },
 {
  "ID+後3碼": 948792124,
  "排名": 60,
  "ID": 948792,
  "姓名": "劉Ｏ仲",
  "經驗值": 15690,
  "獎項": "統一超商100元虛擬商品卡",
  "冰粽": "已完成",
  "鹼粽": "已完成",
  "白粽": "已完成",
  "肉粽": "已完成",
  "嘉興粽": "已完成",
  "全粽達成1000經驗": 1000,
  "FUN粽任務經驗值(中)開啟狀態": "V",
  "FUN粽任務經驗值(中)達成率": "已完成",
  "FUN粽任務經驗值(易)開啟狀態": null,
  "FUN粽任務經驗值(易)達成率": 0
 },
 {
  "ID+後3碼": 868259629,
  "排名": 61,
  "ID": 868259,
  "姓名": "洪Ｏ怡",
  "經驗值": 15680,
  "獎項": "統一超商100元虛擬商品卡",
  "冰粽": "已完成",
  "鹼粽": "已完成",
  "白粽": "已完成",
  "肉粽": "已完成",
  "嘉興粽": "已完成",
  "全粽達成1000經驗": 1000,
  "FUN粽任務經驗值(中)開啟狀態": "V",
  "FUN粽任務經驗值(中)達成率": "已完成",
  "FUN粽任務經驗值(易)開啟狀態": null,
  "FUN粽任務經驗值(易)達成率": 0
 },
 {
  "ID+後3碼": 860170848,
  "排名": 62,
  "ID": 860170,
  "姓名": "潘Ｏ慧",
  "經驗值": 15650,
  "獎項": "統一超商100元虛擬商品卡",
  "冰粽": "已完成",
  "鹼粽": "已完成",
  "白粽": "已完成",
  "肉粽": "已完成",
  "嘉興粽": "已完成",
  "全粽達成1000經驗": 1000,
  "FUN粽任務經驗值(中)開啟狀態": "V",
  "FUN粽任務經驗值(中)達成率": "已完成",
  "FUN粽任務經驗值(易)開啟狀態": null,
  "FUN粽任務經驗值(易)達成率": 0
 },
 {
  "ID+後3碼": 363041037,
  "排名": 63,
  "ID": 363041,
  "姓名": "林Ｏ鈞",
  "經驗值": 15570,
  "獎項": "統一超商100元虛擬商品卡",
  "冰粽": "已完成",
  "鹼粽": "已完成",
  "白粽": 0.5,
  "肉粽": "已完成",
  "嘉興粽": "已完成",
  "全粽達成1000經驗": 0,
  "FUN粽任務經驗值(中)開啟狀態": "V",
  "FUN粽任務經驗值(中)達成率": "已完成",
  "FUN粽任務經驗值(易)開啟狀態": null,
  "FUN粽任務經驗值(易)達成率": 0
 },
 {
  "ID+後3碼": 519365860,
  "排名": 64,
  "ID": 519365,
  "姓名": "潘Ｏ進",
  "經驗值": 15570,
  "獎項": "統一超商100元虛擬商品卡",
  "冰粽": "已完成",
  "鹼粽": "已完成",
  "白粽": "已完成",
  "肉粽": "已完成",
  "嘉興粽": "已完成",
  "全粽達成1000經驗": 1000,
  "FUN粽任務經驗值(中)開啟狀態": "V",
  "FUN粽任務經驗值(中)達成率": "已完成",
  "FUN粽任務經驗值(易)開啟狀態": null,
  "FUN粽任務經驗值(易)達成率": 0
 },
 {
  "ID+後3碼": 1144244245,
  "排名": 65,
  "ID": 1144244,
  "姓名": "洪Ｏ妤",
  "經驗值": 15520,
  "獎項": "統一超商100元虛擬商品卡",
  "冰粽": "已完成",
  "鹼粽": "已完成",
  "白粽": "已完成",
  "肉粽": "已完成",
  "嘉興粽": "已完成",
  "全粽達成1000經驗": 1000,
  "FUN粽任務經驗值(中)開啟狀態": "V",
  "FUN粽任務經驗值(中)達成率": "已完成",
  "FUN粽任務經驗值(易)開啟狀態": null,
  "FUN粽任務經驗值(易)達成率": 0
 },
 {
  "ID+後3碼": 884034901,
  "排名": 66,
  "ID": 884034,
  "姓名": "李Ｏ珊",
  "經驗值": 15470,
  "獎項": "統一超商100元虛擬商品卡",
  "冰粽": "已完成",
  "鹼粽": "已完成",
  "白粽": "已完成",
  "肉粽": "已完成",
  "嘉興粽": "已完成",
  "全粽達成1000經驗": 1000,
  "FUN粽任務經驗值(中)開啟狀態": null,
  "FUN粽任務經驗值(中)達成率": 0,
  "FUN粽任務經驗值(易)開啟狀態": null,
  "FUN粽任務經驗值(易)達成率": 0
 },
 {
  "ID+後3碼": 198450964,
  "排名": 67,
  "ID": 198450,
  "姓名": "陳Ｏ宏",
  "經驗值": 15460,
  "獎項": "統一超商100元虛擬商品卡",
  "冰粽": 0,
  "鹼粽": "已完成",
  "白粽": "已完成",
  "肉粽": "已完成",
  "嘉興粽": "已完成",
  "全粽達成1000經驗": 0,
  "FUN粽任務經驗值(中)開啟狀態": "V",
  "FUN粽任務經驗值(中)達成率": "已完成",
  "FUN粽任務經驗值(易)開啟狀態": null,
  "FUN粽任務經驗值(易)達成率": 0
 },
 {
  "ID+後3碼": 200038788,
  "排名": 68,
  "ID": 200038,
  "姓名": "朱Ｏ榮",
  "經驗值": 15460,
  "獎項": "統一超商100元虛擬商品卡",
  "冰粽": "已完成",
  "鹼粽": "已完成",
  "白粽": "已完成",
  "肉粽": "已完成",
  "嘉興粽": "已完成",
  "全粽達成1000經驗": 1000,
  "FUN粽任務經驗值(中)開啟狀態": "V",
  "FUN粽任務經驗值(中)達成率": "已完成",
  "FUN粽任務經驗值(易)開啟狀態": null,
  "FUN粽任務經驗值(易)達成率": 0
 },
 {
  "ID+後3碼": 219579860,
  "排名": 69,
  "ID": 219579,
  "姓名": "郭Ｏ佑",
  "經驗值": 15450,
  "獎項": "統一超商100元虛擬商品卡",
  "冰粽": "已完成",
  "鹼粽": "已完成",
  "白粽": "已完成",
  "肉粽": "已完成",
  "嘉興粽": "已完成",
  "全粽達成1000經驗": 1000,
  "FUN粽任務經驗值(中)開啟狀態": "V",
  "FUN粽任務經驗值(中)達成率": "已完成",
  "FUN粽任務經驗值(易)開啟狀態": null,
  "FUN粽任務經驗值(易)達成率": 0
 },
 {
  "ID+後3碼": 715338058,
  "排名": 70,
  "ID": 715338,
  "姓名": "游Ｏ瑄",
  "經驗值": 15440,
  "獎項": "統一超商100元虛擬商品卡",
  "冰粽": "已完成",
  "鹼粽": "已完成",
  "白粽": "已完成",
  "肉粽": "已完成",
  "嘉興粽": "已完成",
  "全粽達成1000經驗": 1000,
  "FUN粽任務經驗值(中)開啟狀態": "V",
  "FUN粽任務經驗值(中)達成率": "已完成",
  "FUN粽任務經驗值(易)開啟狀態": null,
  "FUN粽任務經驗值(易)達成率": 0
 },
 {
  "ID+後3碼": 182794447,
  "排名": 71,
  "ID": 182794,
  "姓名": "陳Ｏ豪",
  "經驗值": 15330,
  "獎項": "統一超商100元虛擬商品卡",
  "冰粽": "已完成",
  "鹼粽": "已完成",
  "白粽": "已完成",
  "肉粽": "已完成",
  "嘉興粽": "已完成",
  "全粽達成1000經驗": 1000,
  "FUN粽任務經驗值(中)開啟狀態": "V",
  "FUN粽任務經驗值(中)達成率": "已完成",
  "FUN粽任務經驗值(易)開啟狀態": null,
  "FUN粽任務經驗值(易)達成率": 0
 },
 {
  "ID+後3碼": 906890875,
  "排名": 72,
  "ID": 906890,
  "姓名": "蘇Ｏ弘",
  "經驗值": 15300,
  "獎項": "統一超商100元虛擬商品卡",
  "冰粽": "已完成",
  "鹼粽": "已完成",
  "白粽": "已完成",
  "肉粽": "已完成",
  "嘉興粽": "已完成",
  "全粽達成1000經驗": 1000,
  "FUN粽任務經驗值(中)開啟狀態": "V",
  "FUN粽任務經驗值(中)達成率": "已完成",
  "FUN粽任務經驗值(易)開啟狀態": null,
  "FUN粽任務經驗值(易)達成率": 0
 },
 {
  "ID+後3碼": 223692894,
  "排名": 73,
  "ID": 223692,
  "姓名": "辛Ｏ照",
  "經驗值": 15240,
  "獎項": "統一超商100元虛擬商品卡",
  "冰粽": "已完成",
  "鹼粽": "已完成",
  "白粽": "已完成",
  "肉粽": "已完成",
  "嘉興粽": "已完成",
  "全粽達成1000經驗": 1000,
  "FUN粽任務經驗值(中)開啟狀態": "V",
  "FUN粽任務經驗值(中)達成率": "已完成",
  "FUN粽任務經驗值(易)開啟狀態": null,
  "FUN粽任務經驗值(易)達成率": 0
 },
 {
  "ID+後3碼": 814444967,
  "排名": 74,
  "ID": 814444,
  "姓名": "謝Ｏ逸",
  "經驗值": 15220,
  "獎項": "統一超商100元虛擬商品卡",
  "冰粽": "已完成",
  "鹼粽": "已完成",
  "白粽": "已完成",
  "肉粽": "已完成",
  "嘉興粽": "已完成",
  "全粽達成1000經驗": 1000,
  "FUN粽任務經驗值(中)開啟狀態": "V",
  "FUN粽任務經驗值(中)達成率": "已完成",
  "FUN粽任務經驗值(易)開啟狀態": null,
  "FUN粽任務經驗值(易)達成率": 0
 },
 {
  "ID+後3碼": 182519175,
  "排名": 75,
  "ID": 182519,
  "姓名": "游Ｏ軒",
  "經驗值": 15190,
  "獎項": "統一超商100元虛擬商品卡",
  "冰粽": "已完成",
  "鹼粽": "已完成",
  "白粽": "已完成",
  "肉粽": "已完成",
  "嘉興粽": "已完成",
  "全粽達成1000經驗": 1000,
  "FUN粽任務經驗值(中)開啟狀態": "V",
  "FUN粽任務經驗值(中)達成率": "已完成",
  "FUN粽任務經驗值(易)開啟狀態": null,
  "FUN粽任務經驗值(易)達成率": 0
 },
 {
  "ID+後3碼": 869920787,
  "排名": 76,
  "ID": 869920,
  "姓名": "馮Ｏ誌",
  "經驗值": 15170,
  "獎項": "統一超商100元虛擬商品卡",
  "冰粽": "已完成",
  "鹼粽": "已完成",
  "白粽": "已完成",
  "肉粽": "已完成",
  "嘉興粽": "已完成",
  "全粽達成1000經驗": 1000,
  "FUN粽任務經驗值(中)開啟狀態": "V",
  "FUN粽任務經驗值(中)達成率": "已完成",
  "FUN粽任務經驗值(易)開啟狀態": null,
  "FUN粽任務經驗值(易)達成率": 0
 },
 {
  "ID+後3碼": 209601029,
  "排名": 77,
  "ID": 209601,
  "姓名": "李Ｏ誠",
  "經驗值": 15160,
  "獎項": "統一超商100元虛擬商品卡",
  "冰粽": "已完成",
  "鹼粽": "已完成",
  "白粽": "已完成",
  "肉粽": "已完成",
  "嘉興粽": "已完成",
  "全粽達成1000經驗": 1000,
  "FUN粽任務經驗值(中)開啟狀態": "V",
  "FUN粽任務經驗值(中)達成率": "已完成",
  "FUN粽任務經驗值(易)開啟狀態": null,
  "FUN粽任務經驗值(易)達成率": 0
 },
 {
  "ID+後3碼": 297285037,
  "排名": 78,
  "ID": 297285,
  "姓名": "黃Ｏ諺",
  "經驗值": 15160,
  "獎項": "統一超商100元虛擬商品卡",
  "冰粽": "已完成",
  "鹼粽": "已完成",
  "白粽": "已完成",
  "肉粽": "已完成",
  "嘉興粽": "已完成",
  "全粽達成1000經驗": 1000,
  "FUN粽任務經驗值(中)開啟狀態": "V",
  "FUN粽任務經驗值(中)達成率": "已完成",
  "FUN粽任務經驗值(易)開啟狀態": null,
  "FUN粽任務經驗值(易)達成率": 0
 },
 {
  "ID+後3碼": 878106415,
  "排名": 79,
  "ID": 878106,
  "姓名": "黃Ｏ明",
  "經驗值": 15140,
  "獎項": "統一超商100元虛擬商品卡",
  "冰粽": "已完成",
  "鹼粽": "已完成",
  "白粽": "已完成",
  "肉粽": "已完成",
  "嘉興粽": "已完成",
  "全粽達成1000經驗": 1000,
  "FUN粽任務經驗值(中)開啟狀態": "V",
  "FUN粽任務經驗值(中)達成率": "已完成",
  "FUN粽任務經驗值(易)開啟狀態": null,
  "FUN粽任務經驗值(易)達成率": 0
 },
 {
  "ID+後3碼": 924351457,
  "排名": 80,
  "ID": 924351,
  "姓名": "賴Ｏ鴻",
  "經驗值": 15110,
  "獎項": "統一超商100元虛擬商品卡",
  "冰粽": "已完成",
  "鹼粽": "已完成",
  "白粽": "已完成",
  "肉粽": "已完成",
  "嘉興粽": "已完成",
  "全粽達成1000經驗": 1000,
  "FUN粽任務經驗值(中)開啟狀態": "V",
  "FUN粽任務經驗值(中)達成率": "已完成",
  "FUN粽任務經驗值(易)開啟狀態": null,
  "FUN粽任務經驗值(易)達成率": 0
 },
 {
  "ID+後3碼": 890473851,
  "排名": 81,
  "ID": 890473,
  "姓名": "陳Ｏ勳",
  "經驗值": 15070,
  "獎項": "統一超商100元虛擬商品卡",
  "冰粽": "已完成",
  "鹼粽": "已完成",
  "白粽": "已完成",
  "肉粽": "已完成",
  "嘉興粽": "已完成",
  "全粽達成1000經驗": 1000,
  "FUN粽任務經驗值(中)開啟狀態": "V",
  "FUN粽任務經驗值(中)達成率": "已完成",
  "FUN粽任務經驗值(易)開啟狀態": null,
  "FUN粽任務經驗值(易)達成率": 0
 },
 {
  "ID+後3碼": 717103237,
  "排名": 82,
  "ID": 717103,
  "姓名": "杜Ｏ祥",
  "經驗值": 15060,
  "獎項": "統一超商100元虛擬商品卡",
  "冰粽": "已完成",
  "鹼粽": "已完成",
  "白粽": "已完成",
  "肉粽": "已完成",
  "嘉興粽": "已完成",
  "全粽達成1000經驗": 1000,
  "FUN粽任務經驗值(中)開啟狀態": "V",
  "FUN粽任務經驗值(中)達成率": "已完成",
  "FUN粽任務經驗值(易)開啟狀態": null,
  "FUN粽任務經驗值(易)達成率": 0
 },
 {
  "ID+後3碼": 86412908,
  "排名": 83,
  "ID": 86412,
  "姓名": "趙Ｏ翔",
  "經驗值": 15020,
  "獎項": "統一超商100元虛擬商品卡",
  "冰粽": "已完成",
  "鹼粽": "已完成",
  "白粽": "已完成",
  "肉粽": "已完成",
  "嘉興粽": "已完成",
  "全粽達成1000經驗": 1000,
  "FUN粽任務經驗值(中)開啟狀態": "V",
  "FUN粽任務經驗值(中)達成率": "已完成",
  "FUN粽任務經驗值(易)開啟狀態": null,
  "FUN粽任務經驗值(易)達成率": 0
 },
 {
  "ID+後3碼": 460652079,
  "排名": 84,
  "ID": 460652,
  "姓名": "林Ｏ昇",
  "經驗值": 14990,
  "獎項": "統一超商100元虛擬商品卡",
  "冰粽": "已完成",
  "鹼粽": "已完成",
  "白粽": "已完成",
  "肉粽": "已完成",
  "嘉興粽": "已完成",
  "全粽達成1000經驗": 1000,
  "FUN粽任務經驗值(中)開啟狀態": "V",
  "FUN粽任務經驗值(中)達成率": "已完成",
  "FUN粽任務經驗值(易)開啟狀態": null,
  "FUN粽任務經驗值(易)達成率": 0
 },
 {
  "ID+後3碼": 1106720417,
  "排名": 85,
  "ID": 1106720,
  "姓名": "黃Ｏ倫",
  "經驗值": 14980,
  "獎項": "統一超商100元虛擬商品卡",
  "冰粽": "已完成",
  "鹼粽": "已完成",
  "白粽": "已完成",
  "肉粽": "已完成",
  "嘉興粽": "已完成",
  "全粽達成1000經驗": 1000,
  "FUN粽任務經驗值(中)開啟狀態": "V",
  "FUN粽任務經驗值(中)達成率": "已完成",
  "FUN粽任務經驗值(易)開啟狀態": null,
  "FUN粽任務經驗值(易)達成率": 0
 },
 {
  "ID+後3碼": 617960727,
  "排名": 86,
  "ID": 617960,
  "姓名": "邱Ｏ華",
  "經驗值": 14960,
  "獎項": "統一超商100元虛擬商品卡",
  "冰粽": "已完成",
  "鹼粽": "已完成",
  "白粽": "已完成",
  "肉粽": "已完成",
  "嘉興粽": "已完成",
  "全粽達成1000經驗": 1000,
  "FUN粽任務經驗值(中)開啟狀態": "V",
  "FUN粽任務經驗值(中)達成率": "已完成",
  "FUN粽任務經驗值(易)開啟狀態": null,
  "FUN粽任務經驗值(易)達成率": 0
 },
 {
  "ID+後3碼": 460497955,
  "排名": 87,
  "ID": 460497,
  "姓名": "林Ｏ益",
  "經驗值": 14910,
  "獎項": "統一超商100元虛擬商品卡",
  "冰粽": "已完成",
  "鹼粽": "已完成",
  "白粽": "已完成",
  "肉粽": "已完成",
  "嘉興粽": "已完成",
  "全粽達成1000經驗": 1000,
  "FUN粽任務經驗值(中)開啟狀態": "V",
  "FUN粽任務經驗值(中)達成率": "已完成",
  "FUN粽任務經驗值(易)開啟狀態": null,
  "FUN粽任務經驗值(易)達成率": 0
 },
 {
  "ID+後3碼": 789341864,
  "排名": 88,
  "ID": 789341,
  "姓名": "林Ｏ偉",
  "經驗值": 14900,
  "獎項": "統一超商100元虛擬商品卡",
  "冰粽": "已完成",
  "鹼粽": "已完成",
  "白粽": "已完成",
  "肉粽": "已完成",
  "嘉興粽": "已完成",
  "全粽達成1000經驗": 1000,
  "FUN粽任務經驗值(中)開啟狀態": "V",
  "FUN粽任務經驗值(中)達成率": "已完成",
  "FUN粽任務經驗值(易)開啟狀態": null,
  "FUN粽任務經驗值(易)達成率": 0
 },
 {
  "ID+後3碼": 264278862,
  "排名": 89,
  "ID": 264278,
  "姓名": "楊Ｏ軒",
  "經驗值": 14890,
  "獎項": "統一超商100元虛擬商品卡",
  "冰粽": "已完成",
  "鹼粽": "已完成",
  "白粽": "已完成",
  "肉粽": "已完成",
  "嘉興粽": "已完成",
  "全粽達成1000經驗": 1000,
  "FUN粽任務經驗值(中)開啟狀態": "V",
  "FUN粽任務經驗值(中)達成率": "已完成",
  "FUN粽任務經驗值(易)開啟狀態": null,
  "FUN粽任務經驗值(易)達成率": 0
 },
 {
  "ID+後3碼": 542624854,
  "排名": 90,
  "ID": 542624,
  "姓名": "林Ｏ偉",
  "經驗值": 14830,
  "獎項": "統一超商100元虛擬商品卡",
  "冰粽": "已完成",
  "鹼粽": "已完成",
  "白粽": "已完成",
  "肉粽": "已完成",
  "嘉興粽": "已完成",
  "全粽達成1000經驗": 1000,
  "FUN粽任務經驗值(中)開啟狀態": "V",
  "FUN粽任務經驗值(中)達成率": "已完成",
  "FUN粽任務經驗值(易)開啟狀態": null,
  "FUN粽任務經驗值(易)達成率": 0
 },
 {
  "ID+後3碼": 607038123,
  "排名": 91,
  "ID": 607038,
  "姓名": "黎Ｏ蓮",
  "經驗值": 14790,
  "獎項": "統一超商100元虛擬商品卡",
  "冰粽": "已完成",
  "鹼粽": "已完成",
  "白粽": "已完成",
  "肉粽": "已完成",
  "嘉興粽": "已完成",
  "全粽達成1000經驗": 1000,
  "FUN粽任務經驗值(中)開啟狀態": "V",
  "FUN粽任務經驗值(中)達成率": "已完成",
  "FUN粽任務經驗值(易)開啟狀態": null,
  "FUN粽任務經驗值(易)達成率": 0
 },
 {
  "ID+後3碼": 1102351562,
  "排名": 92,
  "ID": 1102351,
  "姓名": "宋Ｏ倫",
  "經驗值": 14780,
  "獎項": "統一超商100元虛擬商品卡",
  "冰粽": "已完成",
  "鹼粽": "已完成",
  "白粽": "已完成",
  "肉粽": "已完成",
  "嘉興粽": "已完成",
  "全粽達成1000經驗": 1000,
  "FUN粽任務經驗值(中)開啟狀態": "V",
  "FUN粽任務經驗值(中)達成率": "已完成",
  "FUN粽任務經驗值(易)開啟狀態": null,
  "FUN粽任務經驗值(易)達成率": 0
 },
 {
  "ID+後3碼": 140473137,
  "排名": 93,
  "ID": 140473,
  "姓名": "邱Ｏ偉",
  "經驗值": 14770,
  "獎項": "統一超商100元虛擬商品卡",
  "冰粽": "已完成",
  "鹼粽": "已完成",
  "白粽": "已完成",
  "肉粽": "已完成",
  "嘉興粽": "已完成",
  "全粽達成1000經驗": 1000,
  "FUN粽任務經驗值(中)開啟狀態": null,
  "FUN粽任務經驗值(中)達成率": 0,
  "FUN粽任務經驗值(易)開啟狀態": null,
  "FUN粽任務經驗值(易)達成率": 0
 },
 {
  "ID+後3碼": 967677083,
  "排名": 94,
  "ID": 967677,
  "姓名": "陳Ｏ均",
  "經驗值": 14750,
  "獎項": "統一超商100元虛擬商品卡",
  "冰粽": "已完成",
  "鹼粽": "已完成",
  "白粽": "已完成",
  "肉粽": "已完成",
  "嘉興粽": "已完成",
  "全粽達成1000經驗": 1000,
  "FUN粽任務經驗值(中)開啟狀態": "V",
  "FUN粽任務經驗值(中)達成率": "已完成",
  "FUN粽任務經驗值(易)開啟狀態": null,
  "FUN粽任務經驗值(易)達成率": 0
 },
 {
  "ID+後3碼": 809167289,
  "排名": 95,
  "ID": 809167,
  "姓名": "陳Ｏ為",
  "經驗值": 14730,
  "獎項": "統一超商100元虛擬商品卡",
  "冰粽": "已完成",
  "鹼粽": "已完成",
  "白粽": "已完成",
  "肉粽": "已完成",
  "嘉興粽": "已完成",
  "全粽達成1000經驗": 1000,
  "FUN粽任務經驗值(中)開啟狀態": "V",
  "FUN粽任務經驗值(中)達成率": "已完成",
  "FUN粽任務經驗值(易)開啟狀態": null,
  "FUN粽任務經驗值(易)達成率": 0
 },
 {
  "ID+後3碼": 904182758,
  "排名": 96,
  "ID": 904182,
  "姓名": "曾Ｏ強",
  "經驗值": 14710,
  "獎項": "統一超商100元虛擬商品卡",
  "冰粽": "已完成",
  "鹼粽": "已完成",
  "白粽": "已完成",
  "肉粽": "已完成",
  "嘉興粽": "已完成",
  "全粽達成1000經驗": 1000,
  "FUN粽任務經驗值(中)開啟狀態": "V",
  "FUN粽任務經驗值(中)達成率": "已完成",
  "FUN粽任務經驗值(易)開啟狀態": null,
  "FUN粽任務經驗值(易)達成率": 0
 },
 {
  "ID+後3碼": 925280013,
  "排名": 97,
  "ID": 925280,
  "姓名": "林Ｏ麒",
  "經驗值": 14700,
  "獎項": "統一超商100元虛擬商品卡",
  "冰粽": "已完成",
  "鹼粽": "已完成",
  "白粽": "已完成",
  "肉粽": "已完成",
  "嘉興粽": "已完成",
  "全粽達成1000經驗": 1000,
  "FUN粽任務經驗值(中)開啟狀態": "V",
  "FUN粽任務經驗值(中)達成率": "已完成",
  "FUN粽任務經驗值(易)開啟狀態": null,
  "FUN粽任務經驗值(易)達成率": 0
 },
 {
  "ID+後3碼": 788852626,
  "排名": 98,
  "ID": 788852,
  "姓名": "蔡Ｏ興",
  "經驗值": 14700,
  "獎項": "統一超商100元虛擬商品卡",
  "冰粽": "已完成",
  "鹼粽": "已完成",
  "白粽": "已完成",
  "肉粽": "已完成",
  "嘉興粽": "已完成",
  "全粽達成1000經驗": 1000,
  "FUN粽任務經驗值(中)開啟狀態": "V",
  "FUN粽任務經驗值(中)達成率": "已完成",
  "FUN粽任務經驗值(易)開啟狀態": null,
  "FUN粽任務經驗值(易)達成率": 0
 },
 {
  "ID+後3碼": 239682401,
  "排名": 99,
  "ID": 239682,
  "姓名": "黃Ｏ慶",
  "經驗值": 14640,
  "獎項": "統一超商100元虛擬商品卡",
  "冰粽": "已完成",
  "鹼粽": "已完成",
  "白粽": "已完成",
  "肉粽": "已完成",
  "嘉興粽": "已完成",
  "全粽達成1000經驗": 1000,
  "FUN粽任務經驗值(中)開啟狀態": null,
  "FUN粽任務經驗值(中)達成率": 0,
  "FUN粽任務經驗值(易)開啟狀態": null,
  "FUN粽任務經驗值(易)達成率": 0
 },
 {
  "ID+後3碼": 782957792,
  "排名": 100,
  "ID": 782957,
  "姓名": "陳Ｏ豪",
  "經驗值": 14610,
  "獎項": "統一超商100元虛擬商品卡",
  "冰粽": 0.7,
  "鹼粽": "已完成",
  "白粽": "已完成",
  "肉粽": "已完成",
  "嘉興粽": "已完成",
  "全粽達成1000經驗": 0,
  "FUN粽任務經驗值(中)開啟狀態": "V",
  "FUN粽任務經驗值(中)達成率": "已完成",
  "FUN粽任務經驗值(易)開啟狀態": null,
  "FUN粽任務經驗值(易)達成率": 0
 },
 {
  "ID+後3碼": 552019566,
  "排名": 101,
  "ID": 552019,
  "姓名": "蘇Ｏ恒",
  "經驗值": 14600,
  "獎項": "統一超商100元虛擬商品卡",
  "冰粽": "已完成",
  "鹼粽": "已完成",
  "白粽": "已完成",
  "肉粽": "已完成",
  "嘉興粽": "已完成",
  "全粽達成1000經驗": 1000,
  "FUN粽任務經驗值(中)開啟狀態": null,
  "FUN粽任務經驗值(中)達成率": 0,
  "FUN粽任務經驗值(易)開啟狀態": "V",
  "FUN粽任務經驗值(易)達成率": "已完成"
 },
 {
  "ID+後3碼": 629564108,
  "排名": 102,
  "ID": 629564,
  "姓名": "李Ｏ逸",
  "經驗值": 14600,
  "獎項": "統一超商100元虛擬商品卡",
  "冰粽": "已完成",
  "鹼粽": "已完成",
  "白粽": "已完成",
  "肉粽": "已完成",
  "嘉興粽": "已完成",
  "全粽達成1000經驗": 1000,
  "FUN粽任務經驗值(中)開啟狀態": "V",
  "FUN粽任務經驗值(中)達成率": "已完成",
  "FUN粽任務經驗值(易)開啟狀態": null,
  "FUN粽任務經驗值(易)達成率": 0
 },
 {
  "ID+後3碼": 1066089102,
  "排名": 103,
  "ID": 1066089,
  "姓名": "鄭Ｏ航",
  "經驗值": 14580,
  "獎項": "統一超商100元虛擬商品卡",
  "冰粽": "已完成",
  "鹼粽": "已完成",
  "白粽": "已完成",
  "肉粽": "已完成",
  "嘉興粽": "已完成",
  "全粽達成1000經驗": 1000,
  "FUN粽任務經驗值(中)開啟狀態": "V",
  "FUN粽任務經驗值(中)達成率": "已完成",
  "FUN粽任務經驗值(易)開啟狀態": null,
  "FUN粽任務經驗值(易)達成率": 0
 },
 {
  "ID+後3碼": 1147635868,
  "排名": 104,
  "ID": 1147635,
  "姓名": "康Ｏ馳",
  "經驗值": 14560,
  "獎項": "統一超商100元虛擬商品卡",
  "冰粽": "已完成",
  "鹼粽": "已完成",
  "白粽": "已完成",
  "肉粽": "已完成",
  "嘉興粽": "已完成",
  "全粽達成1000經驗": 1000,
  "FUN粽任務經驗值(中)開啟狀態": "V",
  "FUN粽任務經驗值(中)達成率": "已完成",
  "FUN粽任務經驗值(易)開啟狀態": null,
  "FUN粽任務經驗值(易)達成率": 0
 },
 {
  "ID+後3碼": 1064356258,
  "排名": 105,
  "ID": 1064356,
  "姓名": "邱Ｏ宸",
  "經驗值": 14490,
  "獎項": "統一超商100元虛擬商品卡",
  "冰粽": "已完成",
  "鹼粽": "已完成",
  "白粽": "已完成",
  "肉粽": "已完成",
  "嘉興粽": "已完成",
  "全粽達成1000經驗": 1000,
  "FUN粽任務經驗值(中)開啟狀態": "V",
  "FUN粽任務經驗值(中)達成率": "已完成",
  "FUN粽任務經驗值(易)開啟狀態": null,
  "FUN粽任務經驗值(易)達成率": 0
 },
 {
  "ID+後3碼": 880626725,
  "排名": 106,
  "ID": 880626,
  "姓名": "鍾Ｏ堡",
  "經驗值": 14480,
  "獎項": "統一超商100元虛擬商品卡",
  "冰粽": "已完成",
  "鹼粽": "已完成",
  "白粽": "已完成",
  "肉粽": "已完成",
  "嘉興粽": "已完成",
  "全粽達成1000經驗": 1000,
  "FUN粽任務經驗值(中)開啟狀態": "V",
  "FUN粽任務經驗值(中)達成率": "已完成",
  "FUN粽任務經驗值(易)開啟狀態": null,
  "FUN粽任務經驗值(易)達成率": 0
 },
 {
  "ID+後3碼": 466751795,
  "排名": 107,
  "ID": 466751,
  "姓名": "黃Ｏ銘",
  "經驗值": 14470,
  "獎項": "統一超商100元虛擬商品卡",
  "冰粽": "已完成",
  "鹼粽": "已完成",
  "白粽": "已完成",
  "肉粽": "已完成",
  "嘉興粽": "已完成",
  "全粽達成1000經驗": 1000,
  "FUN粽任務經驗值(中)開啟狀態": "V",
  "FUN粽任務經驗值(中)達成率": "已完成",
  "FUN粽任務經驗值(易)開啟狀態": null,
  "FUN粽任務經驗值(易)達成率": 0
 },
 {
  "ID+後3碼": 667073411,
  "排名": 108,
  "ID": 667073,
  "姓名": "徐Ｏ桓",
  "經驗值": 14440,
  "獎項": "統一超商100元虛擬商品卡",
  "冰粽": "已完成",
  "鹼粽": "已完成",
  "白粽": "已完成",
  "肉粽": "已完成",
  "嘉興粽": "已完成",
  "全粽達成1000經驗": 1000,
  "FUN粽任務經驗值(中)開啟狀態": null,
  "FUN粽任務經驗值(中)達成率": 0,
  "FUN粽任務經驗值(易)開啟狀態": null,
  "FUN粽任務經驗值(易)達成率": 0
 },
 {
  "ID+後3碼": 885054599,
  "排名": 109,
  "ID": 885054,
  "姓名": "張Ｏ力",
  "經驗值": 14420,
  "獎項": "統一超商100元虛擬商品卡",
  "冰粽": "已完成",
  "鹼粽": "已完成",
  "白粽": "已完成",
  "肉粽": "已完成",
  "嘉興粽": "已完成",
  "全粽達成1000經驗": 1000,
  "FUN粽任務經驗值(中)開啟狀態": null,
  "FUN粽任務經驗值(中)達成率": 0,
  "FUN粽任務經驗值(易)開啟狀態": "V",
  "FUN粽任務經驗值(易)達成率": "已完成"
 },
 {
  "ID+後3碼": 1110550015,
  "排名": 110,
  "ID": 1110550,
  "姓名": "陳Ｏ順",
  "經驗值": 14370,
  "獎項": "統一超商100元虛擬商品卡",
  "冰粽": "已完成",
  "鹼粽": "已完成",
  "白粽": "已完成",
  "肉粽": "已完成",
  "嘉興粽": "已完成",
  "全粽達成1000經驗": 1000,
  "FUN粽任務經驗值(中)開啟狀態": "V",
  "FUN粽任務經驗值(中)達成率": "已完成",
  "FUN粽任務經驗值(易)開啟狀態": null,
  "FUN粽任務經驗值(易)達成率": 0
 },
 {
  "ID+後3碼": 1174325705,
  "排名": 111,
  "ID": 1174325,
  "姓名": "謝Ｏ翔",
  "經驗值": 14360,
  "獎項": "統一超商100元虛擬商品卡",
  "冰粽": "已完成",
  "鹼粽": "已完成",
  "白粽": "已完成",
  "肉粽": "已完成",
  "嘉興粽": "已完成",
  "全粽達成1000經驗": 1000,
  "FUN粽任務經驗值(中)開啟狀態": null,
  "FUN粽任務經驗值(中)達成率": 0,
  "FUN粽任務經驗值(易)開啟狀態": "V",
  "FUN粽任務經驗值(易)達成率": "已完成"
 },
 {
  "ID+後3碼": 587692138,
  "排名": 112,
  "ID": 587692,
  "姓名": "游Ｏ勳",
  "經驗值": 14320,
  "獎項": "統一超商100元虛擬商品卡",
  "冰粽": "已完成",
  "鹼粽": "已完成",
  "白粽": "已完成",
  "肉粽": "已完成",
  "嘉興粽": "已完成",
  "全粽達成1000經驗": 1000,
  "FUN粽任務經驗值(中)開啟狀態": "V",
  "FUN粽任務經驗值(中)達成率": "已完成",
  "FUN粽任務經驗值(易)開啟狀態": null,
  "FUN粽任務經驗值(易)達成率": 0
 },
 {
  "ID+後3碼": 1093997816,
  "排名": 113,
  "ID": 1093997,
  "姓名": "張Ｏ盛",
  "經驗值": 14300,
  "獎項": "統一超商100元虛擬商品卡",
  "冰粽": "已完成",
  "鹼粽": "已完成",
  "白粽": "已完成",
  "肉粽": "已完成",
  "嘉興粽": "已完成",
  "全粽達成1000經驗": 1000,
  "FUN粽任務經驗值(中)開啟狀態": "V",
  "FUN粽任務經驗值(中)達成率": "已完成",
  "FUN粽任務經驗值(易)開啟狀態": null,
  "FUN粽任務經驗值(易)達成率": 0
 },
 {
  "ID+後3碼": 1106497125,
  "排名": 114,
  "ID": 1106497,
  "姓名": "林Ｏ宏",
  "經驗值": 14290,
  "獎項": "統一超商100元虛擬商品卡",
  "冰粽": "已完成",
  "鹼粽": "已完成",
  "白粽": "已完成",
  "肉粽": "已完成",
  "嘉興粽": "已完成",
  "全粽達成1000經驗": 1000,
  "FUN粽任務經驗值(中)開啟狀態": "V",
  "FUN粽任務經驗值(中)達成率": "已完成",
  "FUN粽任務經驗值(易)開啟狀態": null,
  "FUN粽任務經驗值(易)達成率": 0
 },
 {
  "ID+後3碼": 270200267,
  "排名": 115,
  "ID": 270200,
  "姓名": "張Ｏ峰",
  "經驗值": 14260,
  "獎項": "統一超商100元虛擬商品卡",
  "冰粽": "已完成",
  "鹼粽": "已完成",
  "白粽": "已完成",
  "肉粽": "已完成",
  "嘉興粽": "已完成",
  "全粽達成1000經驗": 1000,
  "FUN粽任務經驗值(中)開啟狀態": "V",
  "FUN粽任務經驗值(中)達成率": "已完成",
  "FUN粽任務經驗值(易)開啟狀態": null,
  "FUN粽任務經驗值(易)達成率": 0
 },
 {
  "ID+後3碼": 848704359,
  "排名": 116,
  "ID": 848704,
  "姓名": "李Ｏ源",
  "經驗值": 14250,
  "獎項": "統一超商100元虛擬商品卡",
  "冰粽": "已完成",
  "鹼粽": "已完成",
  "白粽": "已完成",
  "肉粽": "已完成",
  "嘉興粽": "已完成",
  "全粽達成1000經驗": 1000,
  "FUN粽任務經驗值(中)開啟狀態": null,
  "FUN粽任務經驗值(中)達成率": 0,
  "FUN粽任務經驗值(易)開啟狀態": "V",
  "FUN粽任務經驗值(易)達成率": "已完成"
 },
 {
  "ID+後3碼": 980728195,
  "排名": 117,
  "ID": 980728,
  "姓名": "莊Ｏ閔",
  "經驗值": 14250,
  "獎項": "統一超商100元虛擬商品卡",
  "冰粽": "已完成",
  "鹼粽": "已完成",
  "白粽": "已完成",
  "肉粽": "已完成",
  "嘉興粽": 0.04,
  "全粽達成1000經驗": 0,
  "FUN粽任務經驗值(中)開啟狀態": "V",
  "FUN粽任務經驗值(中)達成率": "已完成",
  "FUN粽任務經驗值(易)開啟狀態": null,
  "FUN粽任務經驗值(易)達成率": 0
 },
 {
  "ID+後3碼": 674217619,
  "排名": 118,
  "ID": 674217,
  "姓名": "廖Ｏ國",
  "經驗值": 14240,
  "獎項": "統一超商100元虛擬商品卡",
  "冰粽": "已完成",
  "鹼粽": "已完成",
  "白粽": "已完成",
  "肉粽": "已完成",
  "嘉興粽": "已完成",
  "全粽達成1000經驗": 1000,
  "FUN粽任務經驗值(中)開啟狀態": "V",
  "FUN粽任務經驗值(中)達成率": "已完成",
  "FUN粽任務經驗值(易)開啟狀態": null,
  "FUN粽任務經驗值(易)達成率": 0
 },
 {
  "ID+後3碼": 996868919,
  "排名": 119,
  "ID": 996868,
  "姓名": "林Ｏ宗",
  "經驗值": 14220,
  "獎項": "統一超商100元虛擬商品卡",
  "冰粽": "已完成",
  "鹼粽": "已完成",
  "白粽": "已完成",
  "肉粽": "已完成",
  "嘉興粽": "已完成",
  "全粽達成1000經驗": 1000,
  "FUN粽任務經驗值(中)開啟狀態": "V",
  "FUN粽任務經驗值(中)達成率": "已完成",
  "FUN粽任務經驗值(易)開啟狀態": null,
  "FUN粽任務經驗值(易)達成率": 0
 },
 {
  "ID+後3碼": 528551497,
  "排名": 120,
  "ID": 528551,
  "姓名": "江Ｏ穎",
  "經驗值": 14220,
  "獎項": "統一超商100元虛擬商品卡",
  "冰粽": "已完成",
  "鹼粽": "已完成",
  "白粽": "已完成",
  "肉粽": "已完成",
  "嘉興粽": "已完成",
  "全粽達成1000經驗": 1000,
  "FUN粽任務經驗值(中)開啟狀態": "V",
  "FUN粽任務經驗值(中)達成率": "已完成",
  "FUN粽任務經驗值(易)開啟狀態": null,
  "FUN粽任務經驗值(易)達成率": 0
 },
 {
  "ID+後3碼": 821543292,
  "排名": 121,
  "ID": 821543,
  "姓名": "朱Ｏ輝",
  "經驗值": 14210,
  "獎項": "統一超商100元虛擬商品卡",
  "冰粽": "已完成",
  "鹼粽": "已完成",
  "白粽": "已完成",
  "肉粽": "已完成",
  "嘉興粽": "已完成",
  "全粽達成1000經驗": 1000,
  "FUN粽任務經驗值(中)開啟狀態": "V",
  "FUN粽任務經驗值(中)達成率": "已完成",
  "FUN粽任務經驗值(易)開啟狀態": null,
  "FUN粽任務經驗值(易)達成率": 0
 },
 {
  "ID+後3碼": 345722032,
  "排名": 122,
  "ID": 345722,
  "姓名": "梁Ｏ弘",
  "經驗值": 14190,
  "獎項": "統一超商100元虛擬商品卡",
  "冰粽": "已完成",
  "鹼粽": "已完成",
  "白粽": "已完成",
  "肉粽": "已完成",
  "嘉興粽": "已完成",
  "全粽達成1000經驗": 1000,
  "FUN粽任務經驗值(中)開啟狀態": "V",
  "FUN粽任務經驗值(中)達成率": "已完成",
  "FUN粽任務經驗值(易)開啟狀態": null,
  "FUN粽任務經驗值(易)達成率": 0
 },
 {
  "ID+後3碼": 869987772,
  "排名": 123,
  "ID": 869987,
  "姓名": "洪Ｏ球",
  "經驗值": 14190,
  "獎項": "統一超商100元虛擬商品卡",
  "冰粽": "已完成",
  "鹼粽": "已完成",
  "白粽": "已完成",
  "肉粽": "已完成",
  "嘉興粽": "已完成",
  "全粽達成1000經驗": 1000,
  "FUN粽任務經驗值(中)開啟狀態": "V",
  "FUN粽任務經驗值(中)達成率": "已完成",
  "FUN粽任務經驗值(易)開啟狀態": null,
  "FUN粽任務經驗值(易)達成率": 0
 },
 {
  "ID+後3碼": 180819959,
  "排名": 124,
  "ID": 180819,
  "姓名": "趙Ｏ瑋",
  "經驗值": 14160,
  "獎項": "統一超商100元虛擬商品卡",
  "冰粽": "已完成",
  "鹼粽": "已完成",
  "白粽": "已完成",
  "肉粽": "已完成",
  "嘉興粽": "已完成",
  "全粽達成1000經驗": 1000,
  "FUN粽任務經驗值(中)開啟狀態": "V",
  "FUN粽任務經驗值(中)達成率": "已完成",
  "FUN粽任務經驗值(易)開啟狀態": null,
  "FUN粽任務經驗值(易)達成率": 0
 },
 {
  "ID+後3碼": 479027711,
  "排名": 125,
  "ID": 479027,
  "姓名": "鄧Ｏ廷",
  "經驗值": 14150,
  "獎項": "統一超商100元虛擬商品卡",
  "冰粽": "已完成",
  "鹼粽": "已完成",
  "白粽": "已完成",
  "肉粽": "已完成",
  "嘉興粽": "已完成",
  "全粽達成1000經驗": 1000,
  "FUN粽任務經驗值(中)開啟狀態": "V",
  "FUN粽任務經驗值(中)達成率": "已完成",
  "FUN粽任務經驗值(易)開啟狀態": null,
  "FUN粽任務經驗值(易)達成率": 0
 },
 {
  "ID+後3碼": 487115812,
  "排名": 126,
  "ID": 487115,
  "姓名": "吳Ｏ翰",
  "經驗值": 14110,
  "獎項": "統一超商100元虛擬商品卡",
  "冰粽": "已完成",
  "鹼粽": "已完成",
  "白粽": "已完成",
  "肉粽": "已完成",
  "嘉興粽": "已完成",
  "全粽達成1000經驗": 1000,
  "FUN粽任務經驗值(中)開啟狀態": "V",
  "FUN粽任務經驗值(中)達成率": "已完成",
  "FUN粽任務經驗值(易)開啟狀態": null,
  "FUN粽任務經驗值(易)達成率": 0
 },
 {
  "ID+後3碼": 641169814,
  "排名": 127,
  "ID": 641169,
  "姓名": "董Ｏ峻",
  "經驗值": 14090,
  "獎項": "統一超商100元虛擬商品卡",
  "冰粽": "已完成",
  "鹼粽": "已完成",
  "白粽": "已完成",
  "肉粽": "已完成",
  "嘉興粽": "已完成",
  "全粽達成1000經驗": 1000,
  "FUN粽任務經驗值(中)開啟狀態": null,
  "FUN粽任務經驗值(中)達成率": 0,
  "FUN粽任務經驗值(易)開啟狀態": null,
  "FUN粽任務經驗值(易)達成率": 0
 },
 {
  "ID+後3碼": 1089321569,
  "排名": 128,
  "ID": 1089321,
  "姓名": "陳Ｏ志",
  "經驗值": 14090,
  "獎項": "統一超商100元虛擬商品卡",
  "冰粽": "已完成",
  "鹼粽": "已完成",
  "白粽": 0,
  "肉粽": "已完成",
  "嘉興粽": "已完成",
  "全粽達成1000經驗": 0,
  "FUN粽任務經驗值(中)開啟狀態": "V",
  "FUN粽任務經驗值(中)達成率": "已完成",
  "FUN粽任務經驗值(易)開啟狀態": null,
  "FUN粽任務經驗值(易)達成率": 0
 },
 {
  "ID+後3碼": 488922809,
  "排名": 129,
  "ID": 488922,
  "姓名": "林Ｏ諺",
  "經驗值": 14090,
  "獎項": "統一超商100元虛擬商品卡",
  "冰粽": 0.3,
  "鹼粽": "已完成",
  "白粽": 0,
  "肉粽": "已完成",
  "嘉興粽": "已完成",
  "全粽達成1000經驗": 0,
  "FUN粽任務經驗值(中)開啟狀態": "V",
  "FUN粽任務經驗值(中)達成率": "已完成",
  "FUN粽任務經驗值(易)開啟狀態": null,
  "FUN粽任務經驗值(易)達成率": 0
 },
 {
  "ID+後3碼": 764153284,
  "排名": 130,
  "ID": 764153,
  "姓名": "廖Ｏ賢",
  "經驗值": 14080,
  "獎項": "統一超商100元虛擬商品卡",
  "冰粽": "已完成",
  "鹼粽": "已完成",
  "白粽": "已完成",
  "肉粽": "已完成",
  "嘉興粽": "已完成",
  "全粽達成1000經驗": 1000,
  "FUN粽任務經驗值(中)開啟狀態": null,
  "FUN粽任務經驗值(中)達成率": 0,
  "FUN粽任務經驗值(易)開啟狀態": "V",
  "FUN粽任務經驗值(易)達成率": "已完成"
 },
 {
  "ID+後3碼": 843318015,
  "排名": 131,
  "ID": 843318,
  "姓名": "江Ｏ鴻",
  "經驗值": 14080,
  "獎項": "統一超商100元虛擬商品卡",
  "冰粽": "已完成",
  "鹼粽": "已完成",
  "白粽": "已完成",
  "肉粽": 0.6,
  "嘉興粽": "已完成",
  "全粽達成1000經驗": 0,
  "FUN粽任務經驗值(中)開啟狀態": "V",
  "FUN粽任務經驗值(中)達成率": "已完成",
  "FUN粽任務經驗值(易)開啟狀態": null,
  "FUN粽任務經驗值(易)達成率": 0
 },
 {
  "ID+後3碼": 721400087,
  "排名": 132,
  "ID": 721400,
  "姓名": "羅Ｏ佳",
  "經驗值": 14070,
  "獎項": "統一超商100元虛擬商品卡",
  "冰粽": "已完成",
  "鹼粽": "已完成",
  "白粽": "已完成",
  "肉粽": "已完成",
  "嘉興粽": "已完成",
  "全粽達成1000經驗": 1000,
  "FUN粽任務經驗值(中)開啟狀態": "V",
  "FUN粽任務經驗值(中)達成率": "已完成",
  "FUN粽任務經驗值(易)開啟狀態": null,
  "FUN粽任務經驗值(易)達成率": 0
 },
 {
  "ID+後3碼": 1058647787,
  "排名": 133,
  "ID": 1058647,
  "姓名": "羅Ｏ言",
  "經驗值": 14060,
  "獎項": "統一超商100元虛擬商品卡",
  "冰粽": "已完成",
  "鹼粽": "已完成",
  "白粽": "已完成",
  "肉粽": "已完成",
  "嘉興粽": "已完成",
  "全粽達成1000經驗": 1000,
  "FUN粽任務經驗值(中)開啟狀態": null,
  "FUN粽任務經驗值(中)達成率": 0,
  "FUN粽任務經驗值(易)開啟狀態": "V",
  "FUN粽任務經驗值(易)達成率": "已完成"
 },
 {
  "ID+後3碼": 672517083,
  "排名": 134,
  "ID": 672517,
  "姓名": "楊Ｏ炎",
  "經驗值": 14050,
  "獎項": "統一超商100元虛擬商品卡",
  "冰粽": "已完成",
  "鹼粽": "已完成",
  "白粽": "已完成",
  "肉粽": "已完成",
  "嘉興粽": "已完成",
  "全粽達成1000經驗": 1000,
  "FUN粽任務經驗值(中)開啟狀態": null,
  "FUN粽任務經驗值(中)達成率": 0,
  "FUN粽任務經驗值(易)開啟狀態": "V",
  "FUN粽任務經驗值(易)達成率": "已完成"
 },
 {
  "ID+後3碼": 351829734,
  "排名": 135,
  "ID": 351829,
  "姓名": "劉Ｏ轅",
  "經驗值": 14040,
  "獎項": "統一超商100元虛擬商品卡",
  "冰粽": "已完成",
  "鹼粽": "已完成",
  "白粽": "已完成",
  "肉粽": "已完成",
  "嘉興粽": "已完成",
  "全粽達成1000經驗": 1000,
  "FUN粽任務經驗值(中)開啟狀態": "V",
  "FUN粽任務經驗值(中)達成率": "已完成",
  "FUN粽任務經驗值(易)開啟狀態": null,
  "FUN粽任務經驗值(易)達成率": 0
 },
 {
  "ID+後3碼": 1172099489,
  "排名": 136,
  "ID": 1172099,
  "姓名": "楊ＯＯ",
  "經驗值": 13970,
  "獎項": "統一超商100元虛擬商品卡",
  "冰粽": "已完成",
  "鹼粽": "已完成",
  "白粽": "已完成",
  "肉粽": "已完成",
  "嘉興粽": "已完成",
  "全粽達成1000經驗": 1000,
  "FUN粽任務經驗值(中)開啟狀態": "V",
  "FUN粽任務經驗值(中)達成率": "已完成",
  "FUN粽任務經驗值(易)開啟狀態": null,
  "FUN粽任務經驗值(易)達成率": 0
 },
 {
  "ID+後3碼": 457771250,
  "排名": 137,
  "ID": 457771,
  "姓名": "李Ｏ廣",
  "經驗值": 13930,
  "獎項": "統一超商100元虛擬商品卡",
  "冰粽": "已完成",
  "鹼粽": "已完成",
  "白粽": "已完成",
  "肉粽": "已完成",
  "嘉興粽": "已完成",
  "全粽達成1000經驗": 1000,
  "FUN粽任務經驗值(中)開啟狀態": null,
  "FUN粽任務經驗值(中)達成率": 0,
  "FUN粽任務經驗值(易)開啟狀態": "V",
  "FUN粽任務經驗值(易)達成率": "已完成"
 },
 {
  "ID+後3碼": 935352654,
  "排名": 138,
  "ID": 935352,
  "姓名": "林Ｏ翔",
  "經驗值": 13910,
  "獎項": "統一超商100元虛擬商品卡",
  "冰粽": "已完成",
  "鹼粽": "已完成",
  "白粽": "已完成",
  "肉粽": "已完成",
  "嘉興粽": 0.84,
  "全粽達成1000經驗": 0,
  "FUN粽任務經驗值(中)開啟狀態": "V",
  "FUN粽任務經驗值(中)達成率": "已完成",
  "FUN粽任務經驗值(易)開啟狀態": null,
  "FUN粽任務經驗值(易)達成率": 0
 },
 {
  "ID+後3碼": 1072283795,
  "排名": 139,
  "ID": 1072283,
  "姓名": "黃Ｏ興",
  "經驗值": 13900,
  "獎項": "統一超商100元虛擬商品卡",
  "冰粽": "已完成",
  "鹼粽": "已完成",
  "白粽": "已完成",
  "肉粽": "已完成",
  "嘉興粽": 0.08,
  "全粽達成1000經驗": 0,
  "FUN粽任務經驗值(中)開啟狀態": "V",
  "FUN粽任務經驗值(中)達成率": "已完成",
  "FUN粽任務經驗值(易)開啟狀態": null,
  "FUN粽任務經驗值(易)達成率": 0
 },
 {
  "ID+後3碼": 790810296,
  "排名": 140,
  "ID": 790810,
  "姓名": "陳Ｏ如",
  "經驗值": 13880,
  "獎項": "Mister Donut 甜甜圈1入",
  "冰粽": "已完成",
  "鹼粽": "已完成",
  "白粽": "已完成",
  "肉粽": "已完成",
  "嘉興粽": "已完成",
  "全粽達成1000經驗": 1000,
  "FUN粽任務經驗值(中)開啟狀態": "V",
  "FUN粽任務經驗值(中)達成率": "已完成",
  "FUN粽任務經驗值(易)開啟狀態": null,
  "FUN粽任務經驗值(易)達成率": 0
 },
 {
  "ID+後3碼": 296245706,
  "排名": 141,
  "ID": 296245,
  "姓名": "劉Ｏ茹",
  "經驗值": 13860,
  "獎項": "Mister Donut 甜甜圈1入",
  "冰粽": "已完成",
  "鹼粽": "已完成",
  "白粽": "已完成",
  "肉粽": "已完成",
  "嘉興粽": "已完成",
  "全粽達成1000經驗": 1000,
  "FUN粽任務經驗值(中)開啟狀態": null,
  "FUN粽任務經驗值(中)達成率": 0,
  "FUN粽任務經驗值(易)開啟狀態": "V",
  "FUN粽任務經驗值(易)達成率": "已完成"
 },
 {
  "ID+後3碼": 1092853977,
  "排名": 142,
  "ID": 1092853,
  "姓名": "葉Ｏ全",
  "經驗值": 13830,
  "獎項": "Mister Donut 甜甜圈1入",
  "冰粽": "已完成",
  "鹼粽": "已完成",
  "白粽": "已完成",
  "肉粽": "已完成",
  "嘉興粽": "已完成",
  "全粽達成1000經驗": 1000,
  "FUN粽任務經驗值(中)開啟狀態": null,
  "FUN粽任務經驗值(中)達成率": 0,
  "FUN粽任務經驗值(易)開啟狀態": "V",
  "FUN粽任務經驗值(易)達成率": "已完成"
 },
 {
  "ID+後3碼": 866424062,
  "排名": 143,
  "ID": 866424,
  "姓名": "江Ｏ銘",
  "經驗值": 13820,
  "獎項": "Mister Donut 甜甜圈1入",
  "冰粽": "已完成",
  "鹼粽": "已完成",
  "白粽": "已完成",
  "肉粽": "已完成",
  "嘉興粽": "已完成",
  "全粽達成1000經驗": 1000,
  "FUN粽任務經驗值(中)開啟狀態": "V",
  "FUN粽任務經驗值(中)達成率": "已完成",
  "FUN粽任務經驗值(易)開啟狀態": null,
  "FUN粽任務經驗值(易)達成率": 0
 },
 {
  "ID+後3碼": 874599703,
  "排名": 144,
  "ID": 874599,
  "姓名": "王Ｏ琳",
  "經驗值": 13780,
  "獎項": "Mister Donut 甜甜圈1入",
  "冰粽": "已完成",
  "鹼粽": "已完成",
  "白粽": "已完成",
  "肉粽": "已完成",
  "嘉興粽": "已完成",
  "全粽達成1000經驗": 1000,
  "FUN粽任務經驗值(中)開啟狀態": null,
  "FUN粽任務經驗值(中)達成率": 0,
  "FUN粽任務經驗值(易)開啟狀態": "V",
  "FUN粽任務經驗值(易)達成率": "已完成"
 },
 {
  "ID+後3碼": 885063429,
  "排名": 145,
  "ID": 885063,
  "姓名": "林Ｏ龍",
  "經驗值": 13780,
  "獎項": "Mister Donut 甜甜圈1入",
  "冰粽": "已完成",
  "鹼粽": "已完成",
  "白粽": "已完成",
  "肉粽": "已完成",
  "嘉興粽": "已完成",
  "全粽達成1000經驗": 1000,
  "FUN粽任務經驗值(中)開啟狀態": "V",
  "FUN粽任務經驗值(中)達成率": "已完成",
  "FUN粽任務經驗值(易)開啟狀態": null,
  "FUN粽任務經驗值(易)達成率": 0
 },
 {
  "ID+後3碼": 236913077,
  "排名": 146,
  "ID": 236913,
  "姓名": "張Ｏ興",
  "經驗值": 13780,
  "獎項": "Mister Donut 甜甜圈1入",
  "冰粽": "已完成",
  "鹼粽": "已完成",
  "白粽": "已完成",
  "肉粽": "已完成",
  "嘉興粽": "已完成",
  "全粽達成1000經驗": 1000,
  "FUN粽任務經驗值(中)開啟狀態": "V",
  "FUN粽任務經驗值(中)達成率": "已完成",
  "FUN粽任務經驗值(易)開啟狀態": null,
  "FUN粽任務經驗值(易)達成率": 0
 },
 {
  "ID+後3碼": 384289056,
  "排名": 147,
  "ID": 384289,
  "姓名": "黃ＯＯ",
  "經驗值": 13760,
  "獎項": "Mister Donut 甜甜圈1入",
  "冰粽": "已完成",
  "鹼粽": "已完成",
  "白粽": "已完成",
  "肉粽": "已完成",
  "嘉興粽": "已完成",
  "全粽達成1000經驗": 1000,
  "FUN粽任務經驗值(中)開啟狀態": null,
  "FUN粽任務經驗值(中)達成率": 0,
  "FUN粽任務經驗值(易)開啟狀態": "V",
  "FUN粽任務經驗值(易)達成率": "已完成"
 },
 {
  "ID+後3碼": 60505907,
  "排名": 148,
  "ID": 60505,
  "姓名": "陳Ｏ威",
  "經驗值": 13720,
  "獎項": "Mister Donut 甜甜圈1入",
  "冰粽": "已完成",
  "鹼粽": "已完成",
  "白粽": "已完成",
  "肉粽": "已完成",
  "嘉興粽": "已完成",
  "全粽達成1000經驗": 1000,
  "FUN粽任務經驗值(中)開啟狀態": "V",
  "FUN粽任務經驗值(中)達成率": "已完成",
  "FUN粽任務經驗值(易)開啟狀態": null,
  "FUN粽任務經驗值(易)達成率": 0
 },
 {
  "ID+後3碼": 802543501,
  "排名": 149,
  "ID": 802543,
  "姓名": "傅Ｏ陵",
  "經驗值": 13710,
  "獎項": "Mister Donut 甜甜圈1入",
  "冰粽": "已完成",
  "鹼粽": "已完成",
  "白粽": "已完成",
  "肉粽": "已完成",
  "嘉興粽": "已完成",
  "全粽達成1000經驗": 1000,
  "FUN粽任務經驗值(中)開啟狀態": null,
  "FUN粽任務經驗值(中)達成率": 0,
  "FUN粽任務經驗值(易)開啟狀態": null,
  "FUN粽任務經驗值(易)達成率": 0
 },
 {
  "ID+後3碼": 888868864,
  "排名": 150,
  "ID": 888868,
  "姓名": "陳Ｏ婷",
  "經驗值": 13700,
  "獎項": "Mister Donut 甜甜圈1入",
  "冰粽": "已完成",
  "鹼粽": "已完成",
  "白粽": "已完成",
  "肉粽": "已完成",
  "嘉興粽": "已完成",
  "全粽達成1000經驗": 1000,
  "FUN粽任務經驗值(中)開啟狀態": "V",
  "FUN粽任務經驗值(中)達成率": "已完成",
  "FUN粽任務經驗值(易)開啟狀態": null,
  "FUN粽任務經驗值(易)達成率": 0
 },
 {
  "ID+後3碼": 721365714,
  "排名": 151,
  "ID": 721365,
  "姓名": "李Ｏ傑",
  "經驗值": 13680,
  "獎項": "Mister Donut 甜甜圈1入",
  "冰粽": "已完成",
  "鹼粽": "已完成",
  "白粽": "已完成",
  "肉粽": "已完成",
  "嘉興粽": "已完成",
  "全粽達成1000經驗": 1000,
  "FUN粽任務經驗值(中)開啟狀態": null,
  "FUN粽任務經驗值(中)達成率": 0,
  "FUN粽任務經驗值(易)開啟狀態": null,
  "FUN粽任務經驗值(易)達成率": 0
 },
 {
  "ID+後3碼": 807493782,
  "排名": 152,
  "ID": 807493,
  "姓名": "楊Ｏ翔",
  "經驗值": 13670,
  "獎項": "Mister Donut 甜甜圈1入",
  "冰粽": "已完成",
  "鹼粽": 0.8,
  "白粽": "已完成",
  "肉粽": 0,
  "嘉興粽": 0,
  "全粽達成1000經驗": 0,
  "FUN粽任務經驗值(中)開啟狀態": "V",
  "FUN粽任務經驗值(中)達成率": "已完成",
  "FUN粽任務經驗值(易)開啟狀態": null,
  "FUN粽任務經驗值(易)達成率": 0
 },
 {
  "ID+後3碼": 341312083,
  "排名": 153,
  "ID": 341312,
  "姓名": "林Ｏ諺",
  "經驗值": 13670,
  "獎項": "Mister Donut 甜甜圈1入",
  "冰粽": "已完成",
  "鹼粽": "已完成",
  "白粽": "已完成",
  "肉粽": "已完成",
  "嘉興粽": "已完成",
  "全粽達成1000經驗": 1000,
  "FUN粽任務經驗值(中)開啟狀態": "V",
  "FUN粽任務經驗值(中)達成率": "已完成",
  "FUN粽任務經驗值(易)開啟狀態": null,
  "FUN粽任務經驗值(易)達成率": 0
 },
 {
  "ID+後3碼": 794064601,
  "排名": 154,
  "ID": 794064,
  "姓名": "林Ｏ豪",
  "經驗值": 13650,
  "獎項": "Mister Donut 甜甜圈1入",
  "冰粽": "已完成",
  "鹼粽": "已完成",
  "白粽": "已完成",
  "肉粽": "已完成",
  "嘉興粽": "已完成",
  "全粽達成1000經驗": 1000,
  "FUN粽任務經驗值(中)開啟狀態": null,
  "FUN粽任務經驗值(中)達成率": 0,
  "FUN粽任務經驗值(易)開啟狀態": "V",
  "FUN粽任務經驗值(易)達成率": "已完成"
 },
 {
  "ID+後3碼": 705950869,
  "排名": 155,
  "ID": 705950,
  "姓名": "鄭Ｏ宇",
  "經驗值": 13640,
  "獎項": "Mister Donut 甜甜圈1入",
  "冰粽": "已完成",
  "鹼粽": "已完成",
  "白粽": "已完成",
  "肉粽": "已完成",
  "嘉興粽": "已完成",
  "全粽達成1000經驗": 1000,
  "FUN粽任務經驗值(中)開啟狀態": "V",
  "FUN粽任務經驗值(中)達成率": "已完成",
  "FUN粽任務經驗值(易)開啟狀態": null,
  "FUN粽任務經驗值(易)達成率": 0
 },
 {
  "ID+後3碼": 288059154,
  "排名": 156,
  "ID": 288059,
  "姓名": "謝Ｏ君",
  "經驗值": 13610,
  "獎項": "Mister Donut 甜甜圈1入",
  "冰粽": "已完成",
  "鹼粽": "已完成",
  "白粽": 0,
  "肉粽": "已完成",
  "嘉興粽": "已完成",
  "全粽達成1000經驗": 0,
  "FUN粽任務經驗值(中)開啟狀態": "V",
  "FUN粽任務經驗值(中)達成率": "已完成",
  "FUN粽任務經驗值(易)開啟狀態": null,
  "FUN粽任務經驗值(易)達成率": 0
 },
 {
  "ID+後3碼": 149065120,
  "排名": 157,
  "ID": 149065,
  "姓名": "徐Ｏ蓁",
  "經驗值": 13610,
  "獎項": "Mister Donut 甜甜圈1入",
  "冰粽": "已完成",
  "鹼粽": "已完成",
  "白粽": "已完成",
  "肉粽": "已完成",
  "嘉興粽": "已完成",
  "全粽達成1000經驗": 1000,
  "FUN粽任務經驗值(中)開啟狀態": "V",
  "FUN粽任務經驗值(中)達成率": "已完成",
  "FUN粽任務經驗值(易)開啟狀態": null,
  "FUN粽任務經驗值(易)達成率": 0
 },
 {
  "ID+後3碼": 911078199,
  "排名": 158,
  "ID": 911078,
  "姓名": "周Ｏ麒",
  "經驗值": 13610,
  "獎項": "Mister Donut 甜甜圈1入",
  "冰粽": "已完成",
  "鹼粽": "已完成",
  "白粽": "已完成",
  "肉粽": "已完成",
  "嘉興粽": "已完成",
  "全粽達成1000經驗": 1000,
  "FUN粽任務經驗值(中)開啟狀態": "V",
  "FUN粽任務經驗值(中)達成率": "已完成",
  "FUN粽任務經驗值(易)開啟狀態": null,
  "FUN粽任務經驗值(易)達成率": 0
 },
 {
  "ID+後3碼": 477092143,
  "排名": 159,
  "ID": 477092,
  "姓名": "張Ｏ豪",
  "經驗值": 13590,
  "獎項": "Mister Donut 甜甜圈1入",
  "冰粽": "已完成",
  "鹼粽": "已完成",
  "白粽": "已完成",
  "肉粽": "已完成",
  "嘉興粽": "已完成",
  "全粽達成1000經驗": 1000,
  "FUN粽任務經驗值(中)開啟狀態": "V",
  "FUN粽任務經驗值(中)達成率": "已完成",
  "FUN粽任務經驗值(易)開啟狀態": null,
  "FUN粽任務經驗值(易)達成率": 0
 },
 {
  "ID+後3碼": 1185456502,
  "排名": 160,
  "ID": 1185456,
  "姓名": "嚴Ｏ昱",
  "經驗值": 13570,
  "獎項": "Mister Donut 甜甜圈1入",
  "冰粽": "已完成",
  "鹼粽": "已完成",
  "白粽": "已完成",
  "肉粽": "已完成",
  "嘉興粽": "已完成",
  "全粽達成1000經驗": 1000,
  "FUN粽任務經驗值(中)開啟狀態": null,
  "FUN粽任務經驗值(中)達成率": 0,
  "FUN粽任務經驗值(易)開啟狀態": null,
  "FUN粽任務經驗值(易)達成率": 0
 },
 {
  "ID+後3碼": 765860218,
  "排名": 161,
  "ID": 765860,
  "姓名": "吳Ｏ得",
  "經驗值": 13570,
  "獎項": "Mister Donut 甜甜圈1入",
  "冰粽": "已完成",
  "鹼粽": "已完成",
  "白粽": "已完成",
  "肉粽": "已完成",
  "嘉興粽": "已完成",
  "全粽達成1000經驗": 1000,
  "FUN粽任務經驗值(中)開啟狀態": null,
  "FUN粽任務經驗值(中)達成率": 0,
  "FUN粽任務經驗值(易)開啟狀態": "V",
  "FUN粽任務經驗值(易)達成率": "已完成"
 },
 {
  "ID+後3碼": 457761327,
  "排名": 162,
  "ID": 457761,
  "姓名": "陳Ｏ倫",
  "經驗值": 13570,
  "獎項": "Mister Donut 甜甜圈1入",
  "冰粽": "已完成",
  "鹼粽": "已完成",
  "白粽": "已完成",
  "肉粽": "已完成",
  "嘉興粽": 0.12,
  "全粽達成1000經驗": 0,
  "FUN粽任務經驗值(中)開啟狀態": "V",
  "FUN粽任務經驗值(中)達成率": "已完成",
  "FUN粽任務經驗值(易)開啟狀態": null,
  "FUN粽任務經驗值(易)達成率": 0
 },
 {
  "ID+後3碼": 807490001,
  "排名": 163,
  "ID": 807490,
  "姓名": "賴Ｏ瑋",
  "經驗值": 13570,
  "獎項": "Mister Donut 甜甜圈1入",
  "冰粽": "已完成",
  "鹼粽": "已完成",
  "白粽": "已完成",
  "肉粽": "已完成",
  "嘉興粽": "已完成",
  "全粽達成1000經驗": 1000,
  "FUN粽任務經驗值(中)開啟狀態": "V",
  "FUN粽任務經驗值(中)達成率": "已完成",
  "FUN粽任務經驗值(易)開啟狀態": null,
  "FUN粽任務經驗值(易)達成率": 0
 },
 {
  "ID+後3碼": 775410232,
  "排名": 164,
  "ID": 775410,
  "姓名": "黃Ｏ憲",
  "經驗值": 13560,
  "獎項": "Mister Donut 甜甜圈1入",
  "冰粽": "已完成",
  "鹼粽": "已完成",
  "白粽": "已完成",
  "肉粽": "已完成",
  "嘉興粽": "已完成",
  "全粽達成1000經驗": 1000,
  "FUN粽任務經驗值(中)開啟狀態": "V",
  "FUN粽任務經驗值(中)達成率": "已完成",
  "FUN粽任務經驗值(易)開啟狀態": null,
  "FUN粽任務經驗值(易)達成率": 0
 },
 {
  "ID+後3碼": 952066269,
  "排名": 165,
  "ID": 952066,
  "姓名": "劉Ｏ志",
  "經驗值": 13530,
  "獎項": "Mister Donut 甜甜圈1入",
  "冰粽": "已完成",
  "鹼粽": "已完成",
  "白粽": "已完成",
  "肉粽": 0.36,
  "嘉興粽": "已完成",
  "全粽達成1000經驗": 0,
  "FUN粽任務經驗值(中)開啟狀態": "V",
  "FUN粽任務經驗值(中)達成率": "已完成",
  "FUN粽任務經驗值(易)開啟狀態": null,
  "FUN粽任務經驗值(易)達成率": 0
 },
 {
  "ID+後3碼": 638518663,
  "排名": 166,
  "ID": 638518,
  "姓名": "陳Ｏ彬",
  "經驗值": 13530,
  "獎項": "Mister Donut 甜甜圈1入",
  "冰粽": "已完成",
  "鹼粽": "已完成",
  "白粽": "已完成",
  "肉粽": "已完成",
  "嘉興粽": "已完成",
  "全粽達成1000經驗": 1000,
  "FUN粽任務經驗值(中)開啟狀態": null,
  "FUN粽任務經驗值(中)達成率": 0,
  "FUN粽任務經驗值(易)開啟狀態": null,
  "FUN粽任務經驗值(易)達成率": 0
 },
 {
  "ID+後3碼": 851403254,
  "排名": 167,
  "ID": 851403,
  "姓名": "蔡Ｏ秀",
  "經驗值": 13530,
  "獎項": "Mister Donut 甜甜圈1入",
  "冰粽": "已完成",
  "鹼粽": "已完成",
  "白粽": "已完成",
  "肉粽": "已完成",
  "嘉興粽": "已完成",
  "全粽達成1000經驗": 1000,
  "FUN粽任務經驗值(中)開啟狀態": "V",
  "FUN粽任務經驗值(中)達成率": "已完成",
  "FUN粽任務經驗值(易)開啟狀態": null,
  "FUN粽任務經驗值(易)達成率": 0
 },
 {
  "ID+後3碼": 855177900,
  "排名": 168,
  "ID": 855177,
  "姓名": "藍Ｏ吉",
  "經驗值": 13530,
  "獎項": "Mister Donut 甜甜圈1入",
  "冰粽": "已完成",
  "鹼粽": "已完成",
  "白粽": "已完成",
  "肉粽": "已完成",
  "嘉興粽": "已完成",
  "全粽達成1000經驗": 1000,
  "FUN粽任務經驗值(中)開啟狀態": "V",
  "FUN粽任務經驗值(中)達成率": "已完成",
  "FUN粽任務經驗值(易)開啟狀態": null,
  "FUN粽任務經驗值(易)達成率": 0
 },
 {
  "ID+後3碼": 353927932,
  "排名": 169,
  "ID": 353927,
  "姓名": "羅Ｏ偉",
  "經驗值": 13520,
  "獎項": "Mister Donut 甜甜圈1入",
  "冰粽": "已完成",
  "鹼粽": "已完成",
  "白粽": "已完成",
  "肉粽": "已完成",
  "嘉興粽": "已完成",
  "全粽達成1000經驗": 1000,
  "FUN粽任務經驗值(中)開啟狀態": "V",
  "FUN粽任務經驗值(中)達成率": "已完成",
  "FUN粽任務經驗值(易)開啟狀態": null,
  "FUN粽任務經驗值(易)達成率": 0
 },
 {
  "ID+後3碼": 1096921491,
  "排名": 170,
  "ID": 1096921,
  "姓名": "林Ｏ偉",
  "經驗值": 13480,
  "獎項": "Mister Donut 甜甜圈1入",
  "冰粽": "已完成",
  "鹼粽": "已完成",
  "白粽": "已完成",
  "肉粽": "已完成",
  "嘉興粽": "已完成",
  "全粽達成1000經驗": 1000,
  "FUN粽任務經驗值(中)開啟狀態": "V",
  "FUN粽任務經驗值(中)達成率": "已完成",
  "FUN粽任務經驗值(易)開啟狀態": null,
  "FUN粽任務經驗值(易)達成率": 0
 },
 {
  "ID+後3碼": 212689269,
  "排名": 171,
  "ID": 212689,
  "姓名": "郭Ｏ峯",
  "經驗值": 13470,
  "獎項": "Mister Donut 甜甜圈1入",
  "冰粽": "已完成",
  "鹼粽": "已完成",
  "白粽": "已完成",
  "肉粽": 0,
  "嘉興粽": "已完成",
  "全粽達成1000經驗": 0,
  "FUN粽任務經驗值(中)開啟狀態": "V",
  "FUN粽任務經驗值(中)達成率": "已完成",
  "FUN粽任務經驗值(易)開啟狀態": null,
  "FUN粽任務經驗值(易)達成率": 0
 },
 {
  "ID+後3碼": 888854595,
  "排名": 172,
  "ID": 888854,
  "姓名": "李Ｏ仁",
  "經驗值": 13450,
  "獎項": "Mister Donut 甜甜圈1入",
  "冰粽": "已完成",
  "鹼粽": "已完成",
  "白粽": "已完成",
  "肉粽": "已完成",
  "嘉興粽": "已完成",
  "全粽達成1000經驗": 1000,
  "FUN粽任務經驗值(中)開啟狀態": "V",
  "FUN粽任務經驗值(中)達成率": "已完成",
  "FUN粽任務經驗值(易)開啟狀態": null,
  "FUN粽任務經驗值(易)達成率": 0
 },
 {
  "ID+後3碼": 818311409,
  "排名": 173,
  "ID": 818311,
  "姓名": "朱Ｏ輝",
  "經驗值": 13440,
  "獎項": "Mister Donut 甜甜圈1入",
  "冰粽": "已完成",
  "鹼粽": "已完成",
  "白粽": "已完成",
  "肉粽": "已完成",
  "嘉興粽": 0,
  "全粽達成1000經驗": 0,
  "FUN粽任務經驗值(中)開啟狀態": "V",
  "FUN粽任務經驗值(中)達成率": "已完成",
  "FUN粽任務經驗值(易)開啟狀態": null,
  "FUN粽任務經驗值(易)達成率": 0
 },
 {
  "ID+後3碼": 864664515,
  "排名": 174,
  "ID": 864664,
  "姓名": "羅Ｏ娟",
  "經驗值": 13440,
  "獎項": "Mister Donut 甜甜圈1入",
  "冰粽": "已完成",
  "鹼粽": "已完成",
  "白粽": "已完成",
  "肉粽": "已完成",
  "嘉興粽": "已完成",
  "全粽達成1000經驗": 1000,
  "FUN粽任務經驗值(中)開啟狀態": null,
  "FUN粽任務經驗值(中)達成率": 0,
  "FUN粽任務經驗值(易)開啟狀態": "V",
  "FUN粽任務經驗值(易)達成率": "已完成"
 },
 {
  "ID+後3碼": 772313822,
  "排名": 175,
  "ID": 772313,
  "姓名": "劉Ｏ婷",
  "經驗值": 13430,
  "獎項": "Mister Donut 甜甜圈1入",
  "冰粽": "已完成",
  "鹼粽": "已完成",
  "白粽": "已完成",
  "肉粽": "已完成",
  "嘉興粽": 0.64,
  "全粽達成1000經驗": 0,
  "FUN粽任務經驗值(中)開啟狀態": "V",
  "FUN粽任務經驗值(中)達成率": "已完成",
  "FUN粽任務經驗值(易)開啟狀態": null,
  "FUN粽任務經驗值(易)達成率": 0
 },
 {
  "ID+後3碼": 930223918,
  "排名": 176,
  "ID": 930223,
  "姓名": "胡Ｏ穎",
  "經驗值": 13430,
  "獎項": "Mister Donut 甜甜圈1入",
  "冰粽": "已完成",
  "鹼粽": "已完成",
  "白粽": "已完成",
  "肉粽": "已完成",
  "嘉興粽": "已完成",
  "全粽達成1000經驗": 1000,
  "FUN粽任務經驗值(中)開啟狀態": "V",
  "FUN粽任務經驗值(中)達成率": "已完成",
  "FUN粽任務經驗值(易)開啟狀態": null,
  "FUN粽任務經驗值(易)達成率": 0
 },
 {
  "ID+後3碼": 191903070,
  "排名": 177,
  "ID": 191903,
  "姓名": "黃Ｏ和",
  "經驗值": 13420,
  "獎項": "Mister Donut 甜甜圈1入",
  "冰粽": "已完成",
  "鹼粽": "已完成",
  "白粽": "已完成",
  "肉粽": "已完成",
  "嘉興粽": "已完成",
  "全粽達成1000經驗": 1000,
  "FUN粽任務經驗值(中)開啟狀態": null,
  "FUN粽任務經驗值(中)達成率": 0,
  "FUN粽任務經驗值(易)開啟狀態": "V",
  "FUN粽任務經驗值(易)達成率": "已完成"
 },
 {
  "ID+後3碼": 179175761,
  "排名": 178,
  "ID": 179175,
  "姓名": "黃Ｏ壹",
  "經驗值": 13420,
  "獎項": "Mister Donut 甜甜圈1入",
  "冰粽": "已完成",
  "鹼粽": "已完成",
  "白粽": "已完成",
  "肉粽": "已完成",
  "嘉興粽": "已完成",
  "全粽達成1000經驗": 1000,
  "FUN粽任務經驗值(中)開啟狀態": "V",
  "FUN粽任務經驗值(中)達成率": "已完成",
  "FUN粽任務經驗值(易)開啟狀態": null,
  "FUN粽任務經驗值(易)達成率": 0
 },
 {
  "ID+後3碼": 629607902,
  "排名": 179,
  "ID": 629607,
  "姓名": "莊Ｏ瑩",
  "經驗值": 13410,
  "獎項": "Mister Donut 甜甜圈1入",
  "冰粽": "已完成",
  "鹼粽": "已完成",
  "白粽": "已完成",
  "肉粽": "已完成",
  "嘉興粽": "已完成",
  "全粽達成1000經驗": 1000,
  "FUN粽任務經驗值(中)開啟狀態": "V",
  "FUN粽任務經驗值(中)達成率": "已完成",
  "FUN粽任務經驗值(易)開啟狀態": null,
  "FUN粽任務經驗值(易)達成率": 0
 },
 {
  "ID+後3碼": 460575188,
  "排名": 180,
  "ID": 460575,
  "姓名": "劉Ｏ諺",
  "經驗值": 13400,
  "獎項": "Mister Donut 甜甜圈1入",
  "冰粽": "已完成",
  "鹼粽": "已完成",
  "白粽": "已完成",
  "肉粽": "已完成",
  "嘉興粽": "已完成",
  "全粽達成1000經驗": 1000,
  "FUN粽任務經驗值(中)開啟狀態": "V",
  "FUN粽任務經驗值(中)達成率": "已完成",
  "FUN粽任務經驗值(易)開啟狀態": null,
  "FUN粽任務經驗值(易)達成率": 0
 },
 {
  "ID+後3碼": 1095506062,
  "排名": 181,
  "ID": 1095506,
  "姓名": "江Ｏ萱",
  "經驗值": 13370,
  "獎項": "Mister Donut 甜甜圈1入",
  "冰粽": "已完成",
  "鹼粽": "已完成",
  "白粽": "已完成",
  "肉粽": "已完成",
  "嘉興粽": "已完成",
  "全粽達成1000經驗": 1000,
  "FUN粽任務經驗值(中)開啟狀態": null,
  "FUN粽任務經驗值(中)達成率": 0,
  "FUN粽任務經驗值(易)開啟狀態": "V",
  "FUN粽任務經驗值(易)達成率": "已完成"
 },
 {
  "ID+後3碼": 911950862,
  "排名": 182,
  "ID": 911950,
  "姓名": "鍾Ｏ盛",
  "經驗值": 13370,
  "獎項": "Mister Donut 甜甜圈1入",
  "冰粽": "已完成",
  "鹼粽": "已完成",
  "白粽": "已完成",
  "肉粽": "已完成",
  "嘉興粽": "已完成",
  "全粽達成1000經驗": 1000,
  "FUN粽任務經驗值(中)開啟狀態": null,
  "FUN粽任務經驗值(中)達成率": 0,
  "FUN粽任務經驗值(易)開啟狀態": "V",
  "FUN粽任務經驗值(易)達成率": "已完成"
 },
 {
  "ID+後3碼": 789361667,
  "排名": 183,
  "ID": 789361,
  "姓名": "吳Ｏ澤",
  "經驗值": 13360,
  "獎項": "Mister Donut 甜甜圈1入",
  "冰粽": "已完成",
  "鹼粽": "已完成",
  "白粽": "已完成",
  "肉粽": "已完成",
  "嘉興粽": "已完成",
  "全粽達成1000經驗": 1000,
  "FUN粽任務經驗值(中)開啟狀態": null,
  "FUN粽任務經驗值(中)達成率": 0,
  "FUN粽任務經驗值(易)開啟狀態": "V",
  "FUN粽任務經驗值(易)達成率": "已完成"
 },
 {
  "ID+後3碼": 281234331,
  "排名": 184,
  "ID": 281234,
  "姓名": "葉Ｏ梅",
  "經驗值": 13360,
  "獎項": "Mister Donut 甜甜圈1入",
  "冰粽": "已完成",
  "鹼粽": "已完成",
  "白粽": "已完成",
  "肉粽": "已完成",
  "嘉興粽": "已完成",
  "全粽達成1000經驗": 1000,
  "FUN粽任務經驗值(中)開啟狀態": null,
  "FUN粽任務經驗值(中)達成率": 0,
  "FUN粽任務經驗值(易)開啟狀態": "V",
  "FUN粽任務經驗值(易)達成率": "已完成"
 },
 {
  "ID+後3碼": 195837519,
  "排名": 185,
  "ID": 195837,
  "姓名": "葛Ｏ成",
  "經驗值": 13350,
  "獎項": "Mister Donut 甜甜圈1入",
  "冰粽": "已完成",
  "鹼粽": "已完成",
  "白粽": "已完成",
  "肉粽": "已完成",
  "嘉興粽": "已完成",
  "全粽達成1000經驗": 1000,
  "FUN粽任務經驗值(中)開啟狀態": "V",
  "FUN粽任務經驗值(中)達成率": "已完成",
  "FUN粽任務經驗值(易)開啟狀態": null,
  "FUN粽任務經驗值(易)達成率": 0
 },
 {
  "ID+後3碼": 608157144,
  "排名": 186,
  "ID": 608157,
  "姓名": "魏Ｏ玉",
  "經驗值": 13340,
  "獎項": "Mister Donut 甜甜圈1入",
  "冰粽": "已完成",
  "鹼粽": "已完成",
  "白粽": "已完成",
  "肉粽": "已完成",
  "嘉興粽": "已完成",
  "全粽達成1000經驗": 1000,
  "FUN粽任務經驗值(中)開啟狀態": null,
  "FUN粽任務經驗值(中)達成率": 0,
  "FUN粽任務經驗值(易)開啟狀態": "V",
  "FUN粽任務經驗值(易)達成率": "已完成"
 },
 {
  "ID+後3碼": 541214771,
  "排名": 187,
  "ID": 541214,
  "姓名": "葉Ｏ雨",
  "經驗值": 13330,
  "獎項": "Mister Donut 甜甜圈1入",
  "冰粽": "已完成",
  "鹼粽": "已完成",
  "白粽": 0,
  "肉粽": "已完成",
  "嘉興粽": "已完成",
  "全粽達成1000經驗": 0,
  "FUN粽任務經驗值(中)開啟狀態": null,
  "FUN粽任務經驗值(中)達成率": 0,
  "FUN粽任務經驗值(易)開啟狀態": "V",
  "FUN粽任務經驗值(易)達成率": "已完成"
 },
 {
  "ID+後3碼": 365018550,
  "排名": 188,
  "ID": 365018,
  "姓名": "何Ｏ環",
  "經驗值": 13310,
  "獎項": "Mister Donut 甜甜圈1入",
  "冰粽": "已完成",
  "鹼粽": "已完成",
  "白粽": "已完成",
  "肉粽": "已完成",
  "嘉興粽": 0.2,
  "全粽達成1000經驗": 0,
  "FUN粽任務經驗值(中)開啟狀態": "V",
  "FUN粽任務經驗值(中)達成率": "已完成",
  "FUN粽任務經驗值(易)開啟狀態": null,
  "FUN粽任務經驗值(易)達成率": 0
 },
 {
  "ID+後3碼": 767750361,
  "排名": 189,
  "ID": 767750,
  "姓名": "陳Ｏ品",
  "經驗值": 13300,
  "獎項": "Mister Donut 甜甜圈1入",
  "冰粽": "已完成",
  "鹼粽": "已完成",
  "白粽": "已完成",
  "肉粽": "已完成",
  "嘉興粽": "已完成",
  "全粽達成1000經驗": 1000,
  "FUN粽任務經驗值(中)開啟狀態": "V",
  "FUN粽任務經驗值(中)達成率": "已完成",
  "FUN粽任務經驗值(易)開啟狀態": null,
  "FUN粽任務經驗值(易)達成率": 0
 },
 {
  "ID+後3碼": 551679019,
  "排名": 190,
  "ID": 551679,
  "姓名": "白Ｏ田",
  "經驗值": 13290,
  "獎項": "Mister Donut 甜甜圈1入",
  "冰粽": "已完成",
  "鹼粽": "已完成",
  "白粽": "已完成",
  "肉粽": "已完成",
  "嘉興粽": "已完成",
  "全粽達成1000經驗": 1000,
  "FUN粽任務經驗值(中)開啟狀態": null,
  "FUN粽任務經驗值(中)達成率": 0,
  "FUN粽任務經驗值(易)開啟狀態": "V",
  "FUN粽任務經驗值(易)達成率": "已完成"
 },
 {
  "ID+後3碼": 1080643981,
  "排名": 191,
  "ID": 1080643,
  "姓名": "游Ｏ豪",
  "經驗值": 13290,
  "獎項": "Mister Donut 甜甜圈1入",
  "冰粽": "已完成",
  "鹼粽": "已完成",
  "白粽": "已完成",
  "肉粽": "已完成",
  "嘉興粽": "已完成",
  "全粽達成1000經驗": 1000,
  "FUN粽任務經驗值(中)開啟狀態": null,
  "FUN粽任務經驗值(中)達成率": 0,
  "FUN粽任務經驗值(易)開啟狀態": null,
  "FUN粽任務經驗值(易)達成率": 0
 },
 {
  "ID+後3碼": 239041647,
  "排名": 192,
  "ID": 239041,
  "姓名": "簡Ｏ宇",
  "經驗值": 13250,
  "獎項": "Mister Donut 甜甜圈1入",
  "冰粽": "已完成",
  "鹼粽": "已完成",
  "白粽": "已完成",
  "肉粽": "已完成",
  "嘉興粽": "已完成",
  "全粽達成1000經驗": 1000,
  "FUN粽任務經驗值(中)開啟狀態": "V",
  "FUN粽任務經驗值(中)達成率": "已完成",
  "FUN粽任務經驗值(易)開啟狀態": null,
  "FUN粽任務經驗值(易)達成率": 0
 },
 {
  "ID+後3碼": 199425287,
  "排名": 193,
  "ID": 199425,
  "姓名": "王Ｏ為",
  "經驗值": 13240,
  "獎項": "Mister Donut 甜甜圈1入",
  "冰粽": "已完成",
  "鹼粽": "已完成",
  "白粽": "已完成",
  "肉粽": "已完成",
  "嘉興粽": "已完成",
  "全粽達成1000經驗": 1000,
  "FUN粽任務經驗值(中)開啟狀態": "V",
  "FUN粽任務經驗值(中)達成率": "已完成",
  "FUN粽任務經驗值(易)開啟狀態": null,
  "FUN粽任務經驗值(易)達成率": 0
 },
 {
  "ID+後3碼": 997588318,
  "排名": 194,
  "ID": 997588,
  "姓名": "詹Ｏ瑛",
  "經驗值": 13230,
  "獎項": "Mister Donut 甜甜圈1入",
  "冰粽": "已完成",
  "鹼粽": "已完成",
  "白粽": "已完成",
  "肉粽": "已完成",
  "嘉興粽": 0.48,
  "全粽達成1000經驗": 0,
  "FUN粽任務經驗值(中)開啟狀態": "V",
  "FUN粽任務經驗值(中)達成率": "已完成",
  "FUN粽任務經驗值(易)開啟狀態": null,
  "FUN粽任務經驗值(易)達成率": 0
 },
 {
  "ID+後3碼": 1105060592,
  "排名": 195,
  "ID": 1105060,
  "姓名": "黃Ｏ捷",
  "經驗值": 13220,
  "獎項": "Mister Donut 甜甜圈1入",
  "冰粽": "已完成",
  "鹼粽": "已完成",
  "白粽": "已完成",
  "肉粽": "已完成",
  "嘉興粽": "已完成",
  "全粽達成1000經驗": 1000,
  "FUN粽任務經驗值(中)開啟狀態": "V",
  "FUN粽任務經驗值(中)達成率": "已完成",
  "FUN粽任務經驗值(易)開啟狀態": null,
  "FUN粽任務經驗值(易)達成率": 0
 },
 {
  "ID+後3碼": 187596725,
  "排名": 196,
  "ID": 187596,
  "姓名": "蔡Ｏ娟",
  "經驗值": 13190,
  "獎項": "Mister Donut 甜甜圈1入",
  "冰粽": "已完成",
  "鹼粽": "已完成",
  "白粽": "已完成",
  "肉粽": "已完成",
  "嘉興粽": "已完成",
  "全粽達成1000經驗": 1000,
  "FUN粽任務經驗值(中)開啟狀態": null,
  "FUN粽任務經驗值(中)達成率": 0,
  "FUN粽任務經驗值(易)開啟狀態": "V",
  "FUN粽任務經驗值(易)達成率": "已完成"
 },
 {
  "ID+後3碼": 752546770,
  "排名": 197,
  "ID": 752546,
  "姓名": "林Ｏ宏",
  "經驗值": 13180,
  "獎項": "Mister Donut 甜甜圈1入",
  "冰粽": "已完成",
  "鹼粽": "已完成",
  "白粽": "已完成",
  "肉粽": "已完成",
  "嘉興粽": "已完成",
  "全粽達成1000經驗": 1000,
  "FUN粽任務經驗值(中)開啟狀態": null,
  "FUN粽任務經驗值(中)達成率": 0,
  "FUN粽任務經驗值(易)開啟狀態": null,
  "FUN粽任務經驗值(易)達成率": 0
 },
 {
  "ID+後3碼": 196309791,
  "排名": 198,
  "ID": 196309,
  "姓名": "吳Ｏ澔",
  "經驗值": 13180,
  "獎項": "Mister Donut 甜甜圈1入",
  "冰粽": "已完成",
  "鹼粽": "已完成",
  "白粽": "已完成",
  "肉粽": "已完成",
  "嘉興粽": "已完成",
  "全粽達成1000經驗": 1000,
  "FUN粽任務經驗值(中)開啟狀態": "V",
  "FUN粽任務經驗值(中)達成率": "已完成",
  "FUN粽任務經驗值(易)開啟狀態": null,
  "FUN粽任務經驗值(易)達成率": 0
 },
 {
  "ID+後3碼": 281249933,
  "排名": 199,
  "ID": 281249,
  "姓名": "林Ｏ慶",
  "經驗值": 13150,
  "獎項": "Mister Donut 甜甜圈1入",
  "冰粽": "已完成",
  "鹼粽": "已完成",
  "白粽": "已完成",
  "肉粽": "已完成",
  "嘉興粽": 0,
  "全粽達成1000經驗": 0,
  "FUN粽任務經驗值(中)開啟狀態": null,
  "FUN粽任務經驗值(中)達成率": 0,
  "FUN粽任務經驗值(易)開啟狀態": "V",
  "FUN粽任務經驗值(易)達成率": "已完成"
 },
 {
  "ID+後3碼": 536468885,
  "排名": 200,
  "ID": 536468,
  "姓名": "趙Ｏ盛",
  "經驗值": 13150,
  "獎項": "Mister Donut 甜甜圈1入",
  "冰粽": "已完成",
  "鹼粽": "已完成",
  "白粽": "已完成",
  "肉粽": "已完成",
  "嘉興粽": "已完成",
  "全粽達成1000經驗": 1000,
  "FUN粽任務經驗值(中)開啟狀態": null,
  "FUN粽任務經驗值(中)達成率": 0,
  "FUN粽任務經驗值(易)開啟狀態": null,
  "FUN粽任務經驗值(易)達成率": 0
 },
 {
  "ID+後3碼": 384359033,
  "排名": 201,
  "ID": 384359,
  "姓名": "郭Ｏ芯",
  "經驗值": 13150,
  "獎項": "Mister Donut 甜甜圈1入",
  "冰粽": "已完成",
  "鹼粽": "已完成",
  "白粽": 0,
  "肉粽": "已完成",
  "嘉興粽": "已完成",
  "全粽達成1000經驗": 0,
  "FUN粽任務經驗值(中)開啟狀態": "V",
  "FUN粽任務經驗值(中)達成率": "已完成",
  "FUN粽任務經驗值(易)開啟狀態": null,
  "FUN粽任務經驗值(易)達成率": 0
 },
 {
  "ID+後3碼": 892653340,
  "排名": 202,
  "ID": 892653,
  "姓名": "游Ｏ如",
  "經驗值": 13150,
  "獎項": "Mister Donut 甜甜圈1入",
  "冰粽": "已完成",
  "鹼粽": "已完成",
  "白粽": "已完成",
  "肉粽": "已完成",
  "嘉興粽": "已完成",
  "全粽達成1000經驗": 1000,
  "FUN粽任務經驗值(中)開啟狀態": null,
  "FUN粽任務經驗值(中)達成率": 0,
  "FUN粽任務經驗值(易)開啟狀態": "V",
  "FUN粽任務經驗值(易)達成率": "已完成"
 },
 {
  "ID+後3碼": 1092852776,
  "排名": 203,
  "ID": 1092852,
  "姓名": "何Ｏ昌",
  "經驗值": 13120,
  "獎項": "Mister Donut 甜甜圈1入",
  "冰粽": "已完成",
  "鹼粽": 0.7,
  "白粽": "已完成",
  "肉粽": 0.4,
  "嘉興粽": 0,
  "全粽達成1000經驗": 0,
  "FUN粽任務經驗值(中)開啟狀態": "V",
  "FUN粽任務經驗值(中)達成率": "已完成",
  "FUN粽任務經驗值(易)開啟狀態": null,
  "FUN粽任務經驗值(易)達成率": 0
 },
 {
  "ID+後3碼": 542715656,
  "排名": 204,
  "ID": 542715,
  "姓名": "賴Ｏ錦",
  "經驗值": 13100,
  "獎項": "Mister Donut 甜甜圈1入",
  "冰粽": "已完成",
  "鹼粽": "已完成",
  "白粽": "已完成",
  "肉粽": "已完成",
  "嘉興粽": "已完成",
  "全粽達成1000經驗": 1000,
  "FUN粽任務經驗值(中)開啟狀態": null,
  "FUN粽任務經驗值(中)達成率": 0,
  "FUN粽任務經驗值(易)開啟狀態": null,
  "FUN粽任務經驗值(易)達成率": 0
 },
 {
  "ID+後3碼": 933697340,
  "排名": 205,
  "ID": 933697,
  "姓名": "陳Ｏ旭",
  "經驗值": 13090,
  "獎項": "Mister Donut 甜甜圈1入",
  "冰粽": "已完成",
  "鹼粽": "已完成",
  "白粽": 0,
  "肉粽": "已完成",
  "嘉興粽": "已完成",
  "全粽達成1000經驗": 0,
  "FUN粽任務經驗值(中)開啟狀態": "V",
  "FUN粽任務經驗值(中)達成率": "已完成",
  "FUN粽任務經驗值(易)開啟狀態": null,
  "FUN粽任務經驗值(易)達成率": 0
 },
 {
  "ID+後3碼": 422193394,
  "排名": 206,
  "ID": 422193,
  "姓名": "張Ｏ茹",
  "經驗值": 13040,
  "獎項": "Mister Donut 甜甜圈1入",
  "冰粽": "已完成",
  "鹼粽": "已完成",
  "白粽": "已完成",
  "肉粽": "已完成",
  "嘉興粽": "已完成",
  "全粽達成1000經驗": 1000,
  "FUN粽任務經驗值(中)開啟狀態": null,
  "FUN粽任務經驗值(中)達成率": 0,
  "FUN粽任務經驗值(易)開啟狀態": "V",
  "FUN粽任務經驗值(易)達成率": "已完成"
 },
 {
  "ID+後3碼": 200015327,
  "排名": 207,
  "ID": 200015,
  "姓名": "楊Ｏ檒",
  "經驗值": 13030,
  "獎項": "Mister Donut 甜甜圈1入",
  "冰粽": "已完成",
  "鹼粽": "已完成",
  "白粽": "已完成",
  "肉粽": "已完成",
  "嘉興粽": 0.6,
  "全粽達成1000經驗": 0,
  "FUN粽任務經驗值(中)開啟狀態": "V",
  "FUN粽任務經驗值(中)達成率": "已完成",
  "FUN粽任務經驗值(易)開啟狀態": null,
  "FUN粽任務經驗值(易)達成率": 0
 },
 {
  "ID+後3碼": 959866184,
  "排名": 208,
  "ID": 959866,
  "姓名": "張Ｏ玉",
  "經驗值": 13020,
  "獎項": "Mister Donut 甜甜圈1入",
  "冰粽": "已完成",
  "鹼粽": "已完成",
  "白粽": 0,
  "肉粽": "已完成",
  "嘉興粽": "已完成",
  "全粽達成1000經驗": 0,
  "FUN粽任務經驗值(中)開啟狀態": "V",
  "FUN粽任務經驗值(中)達成率": "已完成",
  "FUN粽任務經驗值(易)開啟狀態": null,
  "FUN粽任務經驗值(易)達成率": 0
 },
 {
  "ID+後3碼": 377261165,
  "排名": 209,
  "ID": 377261,
  "姓名": "林Ｏ禾",
  "經驗值": 13010,
  "獎項": "Mister Donut 甜甜圈1入",
  "冰粽": "已完成",
  "鹼粽": "已完成",
  "白粽": "已完成",
  "肉粽": 0.52,
  "嘉興粽": "已完成",
  "全粽達成1000經驗": 0,
  "FUN粽任務經驗值(中)開啟狀態": "V",
  "FUN粽任務經驗值(中)達成率": "已完成",
  "FUN粽任務經驗值(易)開啟狀態": null,
  "FUN粽任務經驗值(易)達成率": 0
 },
 {
  "ID+後3碼": 817699066,
  "排名": 210,
  "ID": 817699,
  "姓名": "劉Ｏ雄",
  "經驗值": 12970,
  "獎項": "Mister Donut 甜甜圈1入",
  "冰粽": "已完成",
  "鹼粽": "已完成",
  "白粽": "已完成",
  "肉粽": "已完成",
  "嘉興粽": "已完成",
  "全粽達成1000經驗": 1000,
  "FUN粽任務經驗值(中)開啟狀態": null,
  "FUN粽任務經驗值(中)達成率": 0,
  "FUN粽任務經驗值(易)開啟狀態": "V",
  "FUN粽任務經驗值(易)達成率": "已完成"
 },
 {
  "ID+後3碼": 501824503,
  "排名": 211,
  "ID": 501824,
  "姓名": "謝Ｏ龍",
  "經驗值": 12930,
  "獎項": "Mister Donut 甜甜圈1入",
  "冰粽": "已完成",
  "鹼粽": "已完成",
  "白粽": "已完成",
  "肉粽": "已完成",
  "嘉興粽": "已完成",
  "全粽達成1000經驗": 1000,
  "FUN粽任務經驗值(中)開啟狀態": "V",
  "FUN粽任務經驗值(中)達成率": "已完成",
  "FUN粽任務經驗值(易)開啟狀態": null,
  "FUN粽任務經驗值(易)達成率": 0
 },
 {
  "ID+後3碼": 528482222,
  "排名": 212,
  "ID": 528482,
  "姓名": "黃Ｏ順",
  "經驗值": 12930,
  "獎項": "Mister Donut 甜甜圈1入",
  "冰粽": 0,
  "鹼粽": "已完成",
  "白粽": "已完成",
  "肉粽": "已完成",
  "嘉興粽": "已完成",
  "全粽達成1000經驗": 0,
  "FUN粽任務經驗值(中)開啟狀態": "V",
  "FUN粽任務經驗值(中)達成率": "已完成",
  "FUN粽任務經驗值(易)開啟狀態": null,
  "FUN粽任務經驗值(易)達成率": 0
 },
 {
  "ID+後3碼": 200007252,
  "排名": 213,
  "ID": 200007,
  "姓名": "劉Ｏ中",
  "經驗值": 12920,
  "獎項": "Mister Donut 甜甜圈1入",
  "冰粽": "已完成",
  "鹼粽": "已完成",
  "白粽": "已完成",
  "肉粽": "已完成",
  "嘉興粽": "已完成",
  "全粽達成1000經驗": 1000,
  "FUN粽任務經驗值(中)開啟狀態": null,
  "FUN粽任務經驗值(中)達成率": 0,
  "FUN粽任務經驗值(易)開啟狀態": "V",
  "FUN粽任務經驗值(易)達成率": "已完成"
 },
 {
  "ID+後3碼": 617968404,
  "排名": 214,
  "ID": 617968,
  "姓名": "徐Ｏ君",
  "經驗值": 12900,
  "獎項": "Mister Donut 甜甜圈1入",
  "冰粽": "已完成",
  "鹼粽": "已完成",
  "白粽": "已完成",
  "肉粽": "已完成",
  "嘉興粽": "已完成",
  "全粽達成1000經驗": 1000,
  "FUN粽任務經驗值(中)開啟狀態": null,
  "FUN粽任務經驗值(中)達成率": 0,
  "FUN粽任務經驗值(易)開啟狀態": null,
  "FUN粽任務經驗值(易)達成率": 0
 },
 {
  "ID+後3碼": 478425469,
  "排名": 215,
  "ID": 478425,
  "姓名": "宋Ｏ明",
  "經驗值": 12900,
  "獎項": "Mister Donut 甜甜圈1入",
  "冰粽": "已完成",
  "鹼粽": 0,
  "白粽": "已完成",
  "肉粽": "已完成",
  "嘉興粽": 0,
  "全粽達成1000經驗": 0,
  "FUN粽任務經驗值(中)開啟狀態": "V",
  "FUN粽任務經驗值(中)達成率": "已完成",
  "FUN粽任務經驗值(易)開啟狀態": null,
  "FUN粽任務經驗值(易)達成率": 0
 },
 {
  "ID+後3碼": 996568563,
  "排名": 216,
  "ID": 996568,
  "姓名": "鍾Ｏ陽",
  "經驗值": 12900,
  "獎項": "Mister Donut 甜甜圈1入",
  "冰粽": "已完成",
  "鹼粽": 0.1,
  "白粽": "已完成",
  "肉粽": "已完成",
  "嘉興粽": "已完成",
  "全粽達成1000經驗": 0,
  "FUN粽任務經驗值(中)開啟狀態": "V",
  "FUN粽任務經驗值(中)達成率": "已完成",
  "FUN粽任務經驗值(易)開啟狀態": null,
  "FUN粽任務經驗值(易)達成率": 0
 },
 {
  "ID+後3碼": 384402738,
  "排名": 217,
  "ID": 384402,
  "姓名": "江Ｏ文",
  "經驗值": 12880,
  "獎項": "Mister Donut 甜甜圈1入",
  "冰粽": "已完成",
  "鹼粽": "已完成",
  "白粽": 0,
  "肉粽": "已完成",
  "嘉興粽": "已完成",
  "全粽達成1000經驗": 0,
  "FUN粽任務經驗值(中)開啟狀態": "V",
  "FUN粽任務經驗值(中)達成率": "已完成",
  "FUN粽任務經驗值(易)開啟狀態": null,
  "FUN粽任務經驗值(易)達成率": 0
 },
 {
  "ID+後3碼": 641173957,
  "排名": 218,
  "ID": 641173,
  "姓名": "沈Ｏ千",
  "經驗值": 12880,
  "獎項": "Mister Donut 甜甜圈1入",
  "冰粽": "已完成",
  "鹼粽": "已完成",
  "白粽": "已完成",
  "肉粽": "已完成",
  "嘉興粽": "已完成",
  "全粽達成1000經驗": 1000,
  "FUN粽任務經驗值(中)開啟狀態": "V",
  "FUN粽任務經驗值(中)達成率": "已完成",
  "FUN粽任務經驗值(易)開啟狀態": null,
  "FUN粽任務經驗值(易)達成率": 0
 },
 {
  "ID+後3碼": 460644532,
  "排名": 219,
  "ID": 460644,
  "姓名": "王Ｏ瑋",
  "經驗值": 12880,
  "獎項": "Mister Donut 甜甜圈1入",
  "冰粽": 0,
  "鹼粽": "已完成",
  "白粽": "已完成",
  "肉粽": "已完成",
  "嘉興粽": "已完成",
  "全粽達成1000經驗": 0,
  "FUN粽任務經驗值(中)開啟狀態": "V",
  "FUN粽任務經驗值(中)達成率": "已完成",
  "FUN粽任務經驗值(易)開啟狀態": null,
  "FUN粽任務經驗值(易)達成率": 0
 },
 {
  "ID+後3碼": 788028868,
  "排名": 220,
  "ID": 788028,
  "姓名": "曾Ｏ文",
  "經驗值": 12870,
  "獎項": "Mister Donut 甜甜圈1入",
  "冰粽": "已完成",
  "鹼粽": "已完成",
  "白粽": "已完成",
  "肉粽": "已完成",
  "嘉興粽": "已完成",
  "全粽達成1000經驗": 1000,
  "FUN粽任務經驗值(中)開啟狀態": null,
  "FUN粽任務經驗值(中)達成率": 0,
  "FUN粽任務經驗值(易)開啟狀態": "V",
  "FUN粽任務經驗值(易)達成率": "已完成"
 },
 {
  "ID+後3碼": 296451774,
  "排名": 221,
  "ID": 296451,
  "姓名": "盧Ｏ偉",
  "經驗值": 12870,
  "獎項": "Mister Donut 甜甜圈1入",
  "冰粽": "已完成",
  "鹼粽": "已完成",
  "白粽": "已完成",
  "肉粽": "已完成",
  "嘉興粽": "已完成",
  "全粽達成1000經驗": 1000,
  "FUN粽任務經驗值(中)開啟狀態": null,
  "FUN粽任務經驗值(中)達成率": 0,
  "FUN粽任務經驗值(易)開啟狀態": null,
  "FUN粽任務經驗值(易)達成率": 0
 },
 {
  "ID+後3碼": 765811934,
  "排名": 222,
  "ID": 765811,
  "姓名": "林Ｏ盛",
  "經驗值": 12870,
  "獎項": "Mister Donut 甜甜圈1入",
  "冰粽": "已完成",
  "鹼粽": "已完成",
  "白粽": "已完成",
  "肉粽": "已完成",
  "嘉興粽": "已完成",
  "全粽達成1000經驗": 1000,
  "FUN粽任務經驗值(中)開啟狀態": null,
  "FUN粽任務經驗值(中)達成率": 0,
  "FUN粽任務經驗值(易)開啟狀態": "V",
  "FUN粽任務經驗值(易)達成率": "已完成"
 },
 {
  "ID+後3碼": 1112991953,
  "排名": 223,
  "ID": 1112991,
  "姓名": "石Ｏ廷",
  "經驗值": 12870,
  "獎項": "Mister Donut 甜甜圈1入",
  "冰粽": "已完成",
  "鹼粽": "已完成",
  "白粽": "已完成",
  "肉粽": "已完成",
  "嘉興粽": "已完成",
  "全粽達成1000經驗": 1000,
  "FUN粽任務經驗值(中)開啟狀態": "V",
  "FUN粽任務經驗值(中)達成率": "已完成",
  "FUN粽任務經驗值(易)開啟狀態": null,
  "FUN粽任務經驗值(易)達成率": 0
 },
 {
  "ID+後3碼": 767672128,
  "排名": 224,
  "ID": 767672,
  "姓名": "唐Ｏ妤",
  "經驗值": 12860,
  "獎項": "Mister Donut 甜甜圈1入",
  "冰粽": "已完成",
  "鹼粽": "已完成",
  "白粽": "已完成",
  "肉粽": "已完成",
  "嘉興粽": "已完成",
  "全粽達成1000經驗": 1000,
  "FUN粽任務經驗值(中)開啟狀態": "V",
  "FUN粽任務經驗值(中)達成率": "已完成",
  "FUN粽任務經驗值(易)開啟狀態": null,
  "FUN粽任務經驗值(易)達成率": 0
 },
 {
  "ID+後3碼": 1168770154,
  "排名": 225,
  "ID": 1168770,
  "姓名": "梁Ｏ豪",
  "經驗值": 12860,
  "獎項": "Mister Donut 甜甜圈1入",
  "冰粽": "已完成",
  "鹼粽": "已完成",
  "白粽": "已完成",
  "肉粽": "已完成",
  "嘉興粽": "已完成",
  "全粽達成1000經驗": 1000,
  "FUN粽任務經驗值(中)開啟狀態": null,
  "FUN粽任務經驗值(中)達成率": 0,
  "FUN粽任務經驗值(易)開啟狀態": "V",
  "FUN粽任務經驗值(易)達成率": "已完成"
 },
 {
  "ID+後3碼": 215362008,
  "排名": 226,
  "ID": 215362,
  "姓名": "陳Ｏ豪",
  "經驗值": 12850,
  "獎項": "Mister Donut 甜甜圈1入",
  "冰粽": "已完成",
  "鹼粽": 0.2,
  "白粽": "已完成",
  "肉粽": "已完成",
  "嘉興粽": 0.76,
  "全粽達成1000經驗": 0,
  "FUN粽任務經驗值(中)開啟狀態": null,
  "FUN粽任務經驗值(中)達成率": 0,
  "FUN粽任務經驗值(易)開啟狀態": "V",
  "FUN粽任務經驗值(易)達成率": "已完成"
 },
 {
  "ID+後3碼": 608143149,
  "排名": 227,
  "ID": 608143,
  "姓名": "林Ｏ偉",
  "經驗值": 12850,
  "獎項": "Mister Donut 甜甜圈1入",
  "冰粽": "已完成",
  "鹼粽": "已完成",
  "白粽": "已完成",
  "肉粽": "已完成",
  "嘉興粽": "已完成",
  "全粽達成1000經驗": 1000,
  "FUN粽任務經驗值(中)開啟狀態": null,
  "FUN粽任務經驗值(中)達成率": 0,
  "FUN粽任務經驗值(易)開啟狀態": "V",
  "FUN粽任務經驗值(易)達成率": "已完成"
 },
 {
  "ID+後3碼": 271654314,
  "排名": 228,
  "ID": 271654,
  "姓名": "李Ｏ奕",
  "經驗值": 12840,
  "獎項": "Mister Donut 甜甜圈1入",
  "冰粽": "已完成",
  "鹼粽": "已完成",
  "白粽": "已完成",
  "肉粽": "已完成",
  "嘉興粽": "已完成",
  "全粽達成1000經驗": 1000,
  "FUN粽任務經驗值(中)開啟狀態": null,
  "FUN粽任務經驗值(中)達成率": 0,
  "FUN粽任務經驗值(易)開啟狀態": null,
  "FUN粽任務經驗值(易)達成率": 0
 },
 {
  "ID+後3碼": 1071967328,
  "排名": 229,
  "ID": 1071967,
  "姓名": "黎Ｏ友",
  "經驗值": 12820,
  "獎項": "Mister Donut 甜甜圈1入",
  "冰粽": "已完成",
  "鹼粽": "已完成",
  "白粽": "已完成",
  "肉粽": "已完成",
  "嘉興粽": "已完成",
  "全粽達成1000經驗": 1000,
  "FUN粽任務經驗值(中)開啟狀態": null,
  "FUN粽任務經驗值(中)達成率": 0,
  "FUN粽任務經驗值(易)開啟狀態": null,
  "FUN粽任務經驗值(易)達成率": 0
 },
 {
  "ID+後3碼": 689721971,
  "排名": 230,
  "ID": 689721,
  "姓名": "李Ｏ展",
  "經驗值": 12820,
  "獎項": "Mister Donut 甜甜圈1入",
  "冰粽": "已完成",
  "鹼粽": "已完成",
  "白粽": "已完成",
  "肉粽": "已完成",
  "嘉興粽": "已完成",
  "全粽達成1000經驗": 1000,
  "FUN粽任務經驗值(中)開啟狀態": "V",
  "FUN粽任務經驗值(中)達成率": "已完成",
  "FUN粽任務經驗值(易)開啟狀態": null,
  "FUN粽任務經驗值(易)達成率": 0
 },
 {
  "ID+後3碼": 286645682,
  "排名": 231,
  "ID": 286645,
  "姓名": "陳Ｏ忠",
  "經驗值": 12800,
  "獎項": "Mister Donut 甜甜圈1入",
  "冰粽": 0.7,
  "鹼粽": "已完成",
  "白粽": "已完成",
  "肉粽": "已完成",
  "嘉興粽": "已完成",
  "全粽達成1000經驗": 0,
  "FUN粽任務經驗值(中)開啟狀態": "V",
  "FUN粽任務經驗值(中)達成率": "已完成",
  "FUN粽任務經驗值(易)開啟狀態": null,
  "FUN粽任務經驗值(易)達成率": 0
 },
 {
  "ID+後3碼": 674199530,
  "排名": 232,
  "ID": 674199,
  "姓名": "夏ＯＯ",
  "經驗值": 12770,
  "獎項": "Mister Donut 甜甜圈1入",
  "冰粽": "已完成",
  "鹼粽": "已完成",
  "白粽": "已完成",
  "肉粽": "已完成",
  "嘉興粽": "已完成",
  "全粽達成1000經驗": 1000,
  "FUN粽任務經驗值(中)開啟狀態": null,
  "FUN粽任務經驗值(中)達成率": 0,
  "FUN粽任務經驗值(易)開啟狀態": "V",
  "FUN粽任務經驗值(易)達成率": "已完成"
 },
 {
  "ID+後3碼": 838712185,
  "排名": 233,
  "ID": 838712,
  "姓名": "魏Ｏ敏",
  "經驗值": 12750,
  "獎項": "Mister Donut 甜甜圈1入",
  "冰粽": "已完成",
  "鹼粽": "已完成",
  "白粽": "已完成",
  "肉粽": "已完成",
  "嘉興粽": "已完成",
  "全粽達成1000經驗": 1000,
  "FUN粽任務經驗值(中)開啟狀態": null,
  "FUN粽任務經驗值(中)達成率": 0,
  "FUN粽任務經驗值(易)開啟狀態": "V",
  "FUN粽任務經驗值(易)達成率": "已完成"
 },
 {
  "ID+後3碼": 195853616,
  "排名": 234,
  "ID": 195853,
  "姓名": "許Ｏ瑞",
  "經驗值": 12750,
  "獎項": "Mister Donut 甜甜圈1入",
  "冰粽": "已完成",
  "鹼粽": "已完成",
  "白粽": "已完成",
  "肉粽": "已完成",
  "嘉興粽": "已完成",
  "全粽達成1000經驗": 1000,
  "FUN粽任務經驗值(中)開啟狀態": "V",
  "FUN粽任務經驗值(中)達成率": "已完成",
  "FUN粽任務經驗值(易)開啟狀態": null,
  "FUN粽任務經驗值(易)達成率": 0
 },
 {
  "ID+後3碼": 730171932,
  "排名": 235,
  "ID": 730171,
  "姓名": "李Ｏ賢",
  "經驗值": 12740,
  "獎項": "Mister Donut 甜甜圈1入",
  "冰粽": "已完成",
  "鹼粽": "已完成",
  "白粽": "已完成",
  "肉粽": "已完成",
  "嘉興粽": "已完成",
  "全粽達成1000經驗": 1000,
  "FUN粽任務經驗值(中)開啟狀態": null,
  "FUN粽任務經驗值(中)達成率": 0,
  "FUN粽任務經驗值(易)開啟狀態": null,
  "FUN粽任務經驗值(易)達成率": 0
 },
 {
  "ID+後3碼": 235414128,
  "排名": 236,
  "ID": 235414,
  "姓名": "陸Ｏ昇",
  "經驗值": 12740,
  "獎項": "Mister Donut 甜甜圈1入",
  "冰粽": "已完成",
  "鹼粽": "已完成",
  "白粽": "已完成",
  "肉粽": "已完成",
  "嘉興粽": "已完成",
  "全粽達成1000經驗": 1000,
  "FUN粽任務經驗值(中)開啟狀態": "V",
  "FUN粽任務經驗值(中)達成率": "已完成",
  "FUN粽任務經驗值(易)開啟狀態": null,
  "FUN粽任務經驗值(易)達成率": 0
 },
 {
  "ID+後3碼": 242374293,
  "排名": 237,
  "ID": 242374,
  "姓名": "蔡Ｏ翔",
  "經驗值": 12730,
  "獎項": "Mister Donut 甜甜圈1入",
  "冰粽": "已完成",
  "鹼粽": "已完成",
  "白粽": "已完成",
  "肉粽": "已完成",
  "嘉興粽": "已完成",
  "全粽達成1000經驗": 1000,
  "FUN粽任務經驗值(中)開啟狀態": "V",
  "FUN粽任務經驗值(中)達成率": "已完成",
  "FUN粽任務經驗值(易)開啟狀態": null,
  "FUN粽任務經驗值(易)達成率": 0
 },
 {
  "ID+後3碼": 237157772,
  "排名": 238,
  "ID": 237157,
  "姓名": "柯Ｏ良",
  "經驗值": 12690,
  "獎項": "Mister Donut 甜甜圈1入",
  "冰粽": "已完成",
  "鹼粽": "已完成",
  "白粽": "已完成",
  "肉粽": "已完成",
  "嘉興粽": "已完成",
  "全粽達成1000經驗": 1000,
  "FUN粽任務經驗值(中)開啟狀態": "V",
  "FUN粽任務經驗值(中)達成率": "已完成",
  "FUN粽任務經驗值(易)開啟狀態": null,
  "FUN粽任務經驗值(易)達成率": 0
 },
 {
  "ID+後3碼": 207728591,
  "排名": 239,
  "ID": 207728,
  "姓名": "李Ｏ龍",
  "經驗值": 12660,
  "獎項": "Mister Donut 甜甜圈1入",
  "冰粽": "已完成",
  "鹼粽": "已完成",
  "白粽": "已完成",
  "肉粽": "已完成",
  "嘉興粽": "已完成",
  "全粽達成1000經驗": 1000,
  "FUN粽任務經驗值(中)開啟狀態": null,
  "FUN粽任務經驗值(中)達成率": 0,
  "FUN粽任務經驗值(易)開啟狀態": "V",
  "FUN粽任務經驗值(易)達成率": "已完成"
 }
]